{
"meta":{"test_sets":[],"test_metrics":[],"learn_metrics":[{"best_value":"Min","name":"Logloss"}],"launch_mode":"Train","parameters":"","iteration_count":1000,"learn_sets":["learn"],"name":"experiment"},
"iterations":[
{"learn":[0.6922353766],"iteration":0,"passed_time":0.00318104897,"remaining_time":3.177867921},
{"learn":[0.6906765115],"iteration":1,"passed_time":0.006824512917,"remaining_time":3.405431945},
{"learn":[0.6892721156],"iteration":2,"passed_time":0.009843925938,"remaining_time":3.27146472},
{"learn":[0.6880330307],"iteration":3,"passed_time":0.01179345068,"remaining_time":2.93656922},
{"learn":[0.6864700713],"iteration":4,"passed_time":0.01398258107,"remaining_time":2.782533633},
{"learn":[0.6851630389],"iteration":5,"passed_time":0.01600000902,"remaining_time":2.650668162},
{"learn":[0.6834264662],"iteration":6,"passed_time":0.01820863274,"remaining_time":2.583024616},
{"learn":[0.6817617678],"iteration":7,"passed_time":0.0202645763,"remaining_time":2.512807461},
{"learn":[0.6803317253],"iteration":8,"passed_time":0.02229789395,"remaining_time":2.455245878},
{"learn":[0.6793370827],"iteration":9,"passed_time":0.02393014951,"remaining_time":2.369084802},
{"learn":[0.6780305501],"iteration":10,"passed_time":0.02589784823,"remaining_time":2.328451991},
{"learn":[0.6762530427],"iteration":11,"passed_time":0.0279843721,"remaining_time":2.304046636},
{"learn":[0.6748708105],"iteration":12,"passed_time":0.02984959187,"remaining_time":2.26627286},
{"learn":[0.673678372],"iteration":13,"passed_time":0.03175961059,"remaining_time":2.236784003},
{"learn":[0.6723022352],"iteration":14,"passed_time":0.03370126656,"remaining_time":2.213049838},
{"learn":[0.6716596161],"iteration":15,"passed_time":0.03498847262,"remaining_time":2.151791066},
{"learn":[0.6703846704],"iteration":16,"passed_time":0.03693973039,"remaining_time":2.135985587},
{"learn":[0.6689370708],"iteration":17,"passed_time":0.03890915211,"remaining_time":2.12271041},
{"learn":[0.6674776624],"iteration":18,"passed_time":0.04089701661,"remaining_time":2.111577542},
{"learn":[0.6660565353],"iteration":19,"passed_time":0.04272077591,"remaining_time":2.093318019},
{"learn":[0.6645402647],"iteration":20,"passed_time":0.04489977876,"remaining_time":2.093184924},
{"learn":[0.6631107941],"iteration":21,"passed_time":0.04680457289,"remaining_time":2.080676013},
{"learn":[0.662188934],"iteration":22,"passed_time":0.04841896428,"remaining_time":2.056753396,,
{"learn":[0.6610017506],"iteration":23,"passed_time":0.05017273017,"remaining_time":2.0403576,
{,
{"learn":[0.6597526807],"iteration":24,"passed_time":0.05194921035,"remaining_time":2.0260192,
{,
{"learn":[0.6586029891],"iteration":25,"passed_time":0.05362680245,"remaining_time":2.0089425,
{,
{"learn":[0.6574428287],"iteration":26,"passed_time":0.05524291774,"remaining_time":1.9907910,
{,
{"learn":[0.6559361274],"iteration":27,"passed_time":0.05687352228,"remaining_time":1.9743237,
{,
{"learn":[0.6544554358],"iteration":28,"passed_time":0.05842802501,"remaining_time":1.9563314,
{,
{"learn":[0.6532192489],"iteration":29,"passed_time":0.05996514921,"remaining_time":1.9388731,
{,
{"learn":[0.6517592446],"iteration":30,"passed_time":0.06158298477,"remaining_time":1.924964,
{",
{"learn":[0.6504888691],"iteration":31,"passed_time":0.06305065314,"remaining_time":1.907282,
{",
{"learn":[0.6493937742],"iteration":32,"passed_time":0.06486066032,"remaining_time":1.90061,
{"l,
{"learn":[0.6483800526],"iteration":33,"passed_time":0.06650865342,"remaining_time":1.88962,
{"l,
{"learn":[0.6469108053],"iteration":34,"passed_time":0.06802757904,"remaining_time":1.87561,
{"l,
{"learn":[0.6465209988],"iteration":35,"passed_time":0.06900740017,"remaining_time":1.84786,
{"l,
{"learn":[0.6449000481],"iteration":36,"passed_time":0.07074893922,"remaining_time":1.84138,
{"l,
{"learn":[0.6435271132],"iteration":37,"passed_time":0.07244675449,"remaining_time":1.83404,
{"l,
{"learn":[0.6423489131],"iteration":38,"passed_time":0.07417856419,"remaining_time":1.82783,
{"l,
{"learn":[0.6411417164],"iteration":39,"passed_time":0.07574540128,"remaining_time":1.81788,
{"l,
{"learn":[0.6397205202],"iteration":40,"passed_time":0.07771454145,"remaining_time":1.8177,
{"le,
{"learn":[0.6384853733],"iteration":41,"passed_time":0.07956444646,"remaining_time":1.8148,
{"le,
{"learn":[0.6372382577],"iteration":42,"passed_time":0.08130477549,"remaining_time":1.8095,
{"le,
{"learn":[0.6360283587],"iteration":43,"passed_time":0.08301264905,"remaining_time":1.8036,
{"le,
{"learn":[0.6349739475],"iteration":44,"passed_time":0.08479472921,"remaining_time":1.7995,
{"le,
{"learn":[0.6337204571],"iteration":45,"passed_time":0.08632484932,"remaining_time":1.790,
{"le,
{"learn":[0.6324870811],"iteration":46,"passed_time":0.08785666419,"remaining_time":1.7814,
{"le,
{"learn":[0.6310568429],"iteration":47,"passed_time":0.08950498075,"remaining_time":1.7751,
{"le,
{"learn":[0.6298713541],"iteration":48,"passed_time":0.09128572242,"remaining_time":1.7716,
{"le,
{"learn":[0.6284950816],"iteration":49,"passed_time":0.09287572937,"remaining_time":1.7646,
{"le,
{"learn":[0.6270929685],"iteration":50,"passed_time":0.09454515475,"remaining_time":1.7592,
{"le,
{"learn":[0.6260789506],"iteration":51,"passed_time":0.09616186685,"remaining_time":1.7531,
{"le,
{"learn":[0.6247566362],"iteration":52,"passed_time":0.09786737413,"remaining_time":1.7486,
{"le,
{"learn":[0.6235322689],"iteration":53,"passed_time":0.09971970282,"remaining_time":1.746,
{"le,
{"learn":[0.6222364785],"iteration":54,"passed_time":0.1012320107,"remaining_time":1.739350002},
{"learn":[0.6219943335],"iteration":55,"passed_time":0.1022322463,"remaining_time":1.72334,
{"l,
{"learn":[0.6206308485],"iteration":56,"passed_time":0.1036989243,"remaining_time":1.71558,
{"l,
{"learn":[0.6193625593],"iteration":57,"passed_time":0.1053663378,"remaining_time":1.71129,
{"l,
{"learn":[0.6182647088],"iteration":58,"passed_time":0.1070591116,"remaining_time":1.707502103},
{"learn":[0.6171534764],"iteration":59,"passed_time":0.1088297604,"remaining_time":1.70499958},
{"learn":[0.6160511467],"iteration":60,"passed_time":0.1120147283,"remaining_time":1.724292292},
{"learn":[0.6146807475],"iteration":61,"passed_time":0.1144373677,"remaining_time":1.731326628},
{"learn":[0.6145009],"iteration":62,"passed_time":0.1152314655,"remaining_time":1.71383941,
,
{"learn":[0.613330829],"iteration":63,"passed_time":0.1174248428,"remaining_time":1.71733832,
,
{"learn":[0.6119247126],"iteration":64,"passed_time":0.119225086,"remaining_time":1.715007006},
{"learn":[0.6106980978],"iteration":65,"passed_time":0.1208746572,"remaining_time":1.710559543},
{"learn":[0.610008701],"iteration":66,"passed_time":0.1220672267,"remaining_time":1.699831679},
{"learn":[0.6088804819],"iteration":67,"passed_time":0.1238554435,"remaining_time":1.697548137},
{"learn":[0.6078014767],"iteration":68,"passed_time":0.1255629963,"remaining_time":1.694190574},
{"learn":[0.6062978086],"iteration":69,"passed_time":0.1273162775,"remaining_time":1.691487687},
{"learn":[0.6053210551],"iteration":70,"passed_time":0.1288515466,"remaining_time":1.685958968},
{"learn":[0.6044526517],"iteration":71,"passed_time":0.1303166209,"remaining_time":1.679636447},
{"learn":[0.6033738688],"iteration":72,"passed_time":0.1322761674,"remaining_time":1.679726126},
{"learn":[0.6020676371],"iteration":73,"passed_time":0.1338817798,"remaining_time":1.675331461},
{"learn":[0.6006881119],"iteration":74,"passed_time":0.1357957511,"remaining_time":1.674814264},
{"learn":[0.599611043],"iteration":75,"passed_time":0.1380652831,"remaining_time":1.678583179},
{"learn":[0.598553673],"iteration":76,"passed_time":0.1395870898,"remaining_time":1.673232258},
{"learn":[0.5971299715],"iteration":77,"passed_time":0.1412923984,"remaining_time":1.670148607},
{"learn":[0.5957843903],"iteration":78,"passed_time":0.1428237031,"remaining_time":1.665071272},
{"learn":[0.5946291127],"iteration":79,"passed_time":0.1444786319,"remaining_time":1.661504267},
{"learn":[0.5934697473],"iteration":80,"passed_time":0.1460603865,"remaining_time":1.657154261},
{"learn":[0.5924245475],"iteration":81,"passed_time":0.1478320976,"remaining_time":1.654998361},
{"learn":[0.5911967537],"iteration":82,"passed_time":0.1493043674,"remaining_time":1.649543432},
{"learn":[0.5899367876],"iteration":83,"passed_time":0.1509298822,"remaining_time":1.64585443},
{"learn":[0.5886341899],"iteration":84,"passed_time":0.1528244057,"remaining_time":1.645109779},
{"learn":[0.58730111],"iteration":85,"passed_time":0.1542878272,"remaining_time":1.639756675},
{"learn":[0.5862552193],"iteration":86,"passed_time":0.1559534776,"remaining_time":1.636615231},
{"learn":[0.5851528828],"iteration":87,"passed_time":0.1575479584,"remaining_time":1.63276975},
{"learn":[0.5841628599],"iteration":88,"passed_time":0.1592570693,"remaining_time":1.630148204},
{"learn":[0.5829552142],"iteration":89,"passed_time":0.1608051329,"remaining_time":1.625918566},
{"learn":[0.5817515962],"iteration":90,"passed_time":0.1626844127,"remaining_time":1.625056386},
{"learn":[0.5804220267],"iteration":91,"passed_time":0.1643376532,"remaining_time":1.621941186},
{"learn":[0.5794789449],"iteration":92,"passed_time":0.16604094,"remaining_time":1.619345511},
{"learn":[0.5789929117],"iteration":93,"passed_time":0.1668733392,"remaining_time":1.60837495},
{"learn":[0.5780811024],"iteration":94,"passed_time":0.1686780052,"remaining_time":1.606879944},
{"learn":[0.5769037785],"iteration":95,"passed_time":0.1702539165,"remaining_time":1.60322438},
{"learn":[0.5759010907],"iteration":96,"passed_time":0.17186723,"remaining_time":1.599959883},
{"learn":[0.5747314081],"iteration":97,"passed_time":0.1735256941,"remaining_time":1.597144654},
{"learn":[0.5736318915],"iteration":98,"passed_time":0.1751160264,"remaining_time":1.593732725},
{"learn":[0.5726546456],"iteration":99,"passed_time":0.1766061129,"remaining_time":1.589455016},
{"learn":[0.5724557213],"iteration":100,"passed_time":0.1773770417,"remaining_time":1.578831292},
{"learn":[0.5714534455],"iteration":101,"passed_time":0.1790196581,"remaining_time":1.576075029},
{"learn":[0.5704446435],"iteration":102,"passed_time":0.1806954105,"remaining_time":1.573628964},
{"learn":[0.5693075271],"iteration":103,"passed_time":0.1823509535,"remaining_time":1.571023599},
{"learn":[0.5684439117],"iteration":104,"passed_time":0.1841001682,"remaining_time":1.569234767},
{"learn":[0.5673432616],"iteration":105,"passed_time":0.1858287013,"remaining_time":1.567272255},
{"learn":[0.5661587672],"iteration":106,"passed_time":0.1873374456,"remaining_time":1.563479803},
{"learn":[0.5650843568],"iteration":107,"passed_time":0.1888192452,"remaining_time":1.559507099},
{"learn":[0.5639704996],"iteration":108,"passed_time":0.1902668808,"remaining_time":1.555300833},
{"learn":[0.5628139181],"iteration":109,"passed_time":0.1917328963,"remaining_time":1.551293434},
{"learn":[0.561698951],"iteration":110,"passed_time":0.1936146418,"remaining_time":1.55066141},
{"learn":[0.5606456917],"iteration":111,"passed_time":0.1951638006,"remaining_time":1.547370133},
{"learn":[0.5595368787],"iteration":112,"passed_time":0.1968982964,"remaining_time":1.545564503},
{"learn":[0.5585069255],"iteration":113,"passed_time":0.1986430309,"remaining_time":1.543839696},
{"learn":[0.5574184927],"iteration":114,"passed_time":0.2002702304,"remaining_time":1.541210034},
{"learn":[0.5564465334],"iteration":115,"passed_time":0.2017511725,"remaining_time":1.537483074},
{"learn":[0.5556838989],"iteration":116,"passed_time":0.2027985115,"remaining_time":1.530522099},
{"learn":[0.5546302708],"iteration":117,"passed_time":0.2043733831,"remaining_time":1.52760444},
{"learn":[0.5534686554],"iteration":118,"passed_time":0.2058252046,"remaining_time":1.523798364},
{"learn":[0.5525627318],"iteration":119,"passed_time":0.207433638,"remaining_time":1.521180012},
{"learn":[0.5520814502],"iteration":120,"passed_time":0.2084389187,"remaining_time":1.514196773},
{"learn":[0.5511154884],"iteration":121,"passed_time":0.2102917649,"remaining_time":1.513411226},
{"learn":[0.5499295279],"iteration":122,"passed_time":0.2120166926,"remaining_time":1.511696256},
{"learn":[0.548735522],"iteration":123,"passed_time":0.2137854507,"remaining_time":1.510290765},
{"learn":[0.5475872711],"iteration":124,"passed_time":0.215723791,"remaining_time":1.510066537},
{"learn":[0.5466054375],"iteration":125,"passed_time":0.2174873027,"remaining_time":1.508602401},
{"learn":[0.5455189289],"iteration":126,"passed_time":0.2191981457,"remaining_time":1.506771505},
{"learn":[0.5445310358],"iteration":127,"passed_time":0.2208150746,"remaining_time":1.504302696},
{"learn":[0.543523891],"iteration":128,"passed_time":0.2224398915,"remaining_time":1.501900353},
{"learn":[0.542329662],"iteration":129,"passed_time":0.2241944583,"remaining_time":1.500378298},
{"learn":[0.5413219847],"iteration":130,"passed_time":0.2258086255,"remaining_time":1.49792134},
{"learn":[0.5401257046],"iteration":131,"passed_time":0.2273839528,"remaining_time":1.49522175},
{"learn":[0.5392160633],"iteration":132,"passed_time":0.2291608958,"remaining_time":1.493853359},
{"learn":[0.538063746],"iteration":133,"passed_time":0.2307478058,"remaining_time":1.491250745},
{"learn":[0.5379198224],"iteration":134,"passed_time":0.2314606509,"remaining_time":1.483062689},
{"learn":[0.5369290177],"iteration":135,"passed_time":0.2330975926,"remaining_time":1.480855294},
{"learn":[0.5358821367],"iteration":136,"passed_time":0.2347479447,"remaining_time":1.478740703},
{"learn":[0.5349938179],"iteration":137,"passed_time":0.2363827834,"remaining_time":1.476535937},
{"learn":[0.5340102011],"iteration":138,"passed_time":0.2380662251,"remaining_time":1.47464043},
{"learn":[0.5330274153],"iteration":139,"passed_time":0.2396051589,"remaining_time":1.471860262},
{"learn":[0.5319260108],"iteration":140,"passed_time":0.2412566946,"remaining_time":1.469783692},
{"learn":[0.5310707283],"iteration":141,"passed_time":0.2427115439,"remaining_time":1.46652468},
{"learn":[0.5301563916],"iteration":142,"passed_time":0.2443443452,"remaining_time":1.464357369},
{"learn":[0.5291486929],"iteration":143,"passed_time":0.2459696067,"remaining_time":1.462152662},
{"learn":[0.5280417204],"iteration":144,"passed_time":0.2476140682,"remaining_time":1.460069161},
{"learn":[0.5276498498],"iteration":145,"passed_time":0.2485357564,"remaining_time":1.453763945},
{"learn":[0.5268638806],"iteration":146,"passed_time":0.2501704585,"remaining_time":1.451669395},
{"learn":[0.5260240475],"iteration":147,"passed_time":0.2518513808,"remaining_time":1.449847138},
{"learn":[0.52504739],"iteration":148,"passed_time":0.2534606306,"remaining_time":1.447617427},
{"learn":[0.5239085195],"iteration":149,"passed_time":0.2551105006,"remaining_time":1.44562617},
{"learn":[0.522875101],"iteration":150,"passed_time":0.2566841632,"remaining_time":1.443210957},
{"learn":[0.5219336918],"iteration":151,"passed_time":0.2584240084,"remaining_time":1.441733942},
{"learn":[0.5213516601],"iteration":152,"passed_time":0.2596171683,"remaining_time":1.437227069},
{"learn":[0.5205815958],"iteration":153,"passed_time":0.2610688987,"remaining_time":1.43418369},
{"learn":[0.5196460724],"iteration":154,"passed_time":0.2627023014,"remaining_time":1.432151256},
{"learn":[0.5186675493],"iteration":155,"passed_time":0.2643939581,"remaining_time":1.430439107},
{"learn":[0.5178570248],"iteration":156,"passed_time":0.2660717288,"remaining_time":1.428652659},
{"learn":[0.5168075099],"iteration":157,"passed_time":0.2677106896,"remaining_time":1.426660764},
{"learn":[0.5158645916],"iteration":158,"passed_time":0.2692682019,"remaining_time":1.424242502},
{"learn":[0.5148616901],"iteration":159,"passed_time":0.271038355,"remaining_time":1.422951364},
{"learn":[0.5137350016],"iteration":160,"passed_time":0.2726407719,"remaining_time":1.420780172},
{"learn":[0.5131566274],"iteration":161,"passed_time":0.2736417656,"remaining_time":1.415504936},
{"learn":[0.5122493369],"iteration":162,"passed_time":0.2755946981,"remaining_time":1.415170321},
{"learn":[0.5114661865],"iteration":163,"passed_time":0.2774064219,"remaining_time":1.414096151},
{"learn":[0.510416785],"iteration":164,"passed_time":0.2790360224,"remaining_time":1.412091386},
{"learn":[0.5094194329],"iteration":165,"passed_time":0.2808260415,"remaining_time":1.4108971},
{"learn":[0.5084754787],"iteration":166,"passed_time":0.2823329371,"remaining_time":1.408283452},
{"learn":[0.5075274541],"iteration":167,"passed_time":0.2840535076,"remaining_time":1.406741181},
{"learn":[0.5073717959],"iteration":168,"passed_time":0.2848573666,"remaining_time":1.400689181},
{"learn":[0.5065710243],"iteration":169,"passed_time":0.2866372108,"remaining_time":1.399464029},
{"learn":[0.505463278],"iteration":170,"passed_time":0.2882935902,"remaining_time":1.397633838},
{"learn":[0.5045517323],"iteration":171,"passed_time":0.2901784181,"remaining_time":1.396905408},
{"learn":[0.5035006037],"iteration":172,"passed_time":0.291837377,"remaining_time":1.395083877},
{"learn":[0.502524364],"iteration":173,"passed_time":0.2935936103,"remaining_time":1.393725989},
{"learn":[0.5014526804],"iteration":174,"passed_time":0.295204584,"remaining_time":1.391678753},
{"learn":[0.5002711585],"iteration":175,"passed_time":0.2968681315,"remaining_time":1.389882615},
{"learn":[0.4993842989],"iteration":176,"passed_time":0.2987024566,"remaining_time":1.388882044},
{"learn":[0.4985725819],"iteration":177,"passed_time":0.3017885619,"remaining_time":1.393652797},
{"learn":[0.4975854397],"iteration":178,"passed_time":0.3035514229,"remaining_time":1.392266582},
{"learn":[0.4967314358],"iteration":179,"passed_time":0.3052212128,"remaining_time":1.390452192},
{"learn":[0.4956801644],"iteration":180,"passed_time":0.3069110654,"remaining_time":1.38873018},
{"learn":[0.4947984394],"iteration":181,"passed_time":0.3086379959,"remaining_time":1.387175168},
{"learn":[0.4938534134],"iteration":182,"passed_time":0.3103480963,"remaining_time":1.38554314},
{"learn":[0.4929232205],"iteration":183,"passed_time":0.3119973769,"remaining_time":1.383640541},
{"learn":[0.4920247862],"iteration":184,"passed_time":0.313707265,"remaining_time":1.382007681},
{"learn":[0.4909306157],"iteration":185,"passed_time":0.3156824097,"remaining_time":1.381534847},
{"learn":[0.48999597],"iteration":186,"passed_time":0.3175815,"remaining_time":1.380715291},
{"learn":[0.4889079454],"iteration":187,"passed_time":0.3191115026,"remaining_time":1.378290107},
{"learn":[0.4880862567],"iteration":188,"passed_time":0.3206438532,"remaining_time":1.375884471},
{"learn":[0.4872113374],"iteration":189,"passed_time":0.3222635557,"remaining_time":1.373860422},
{"learn":[0.4862513049],"iteration":190,"passed_time":0.3242037721,"remaining_time":1.373198176},
{"learn":[0.485364062],"iteration":191,"passed_time":0.3259301257,"remaining_time":1.371622613},
{"learn":[0.4843640728],"iteration":192,"passed_time":0.327600322,"remaining_time":1.369810673},
{"learn":[0.4834007672],"iteration":193,"passed_time":0.3291447901,"remaining_time":1.367477839},
{"learn":[0.4825198474],"iteration":194,"passed_time":0.3305269079,"remaining_time":1.364482876},
{"learn":[0.4817249624],"iteration":195,"passed_time":0.3320583511,"remaining_time":1.362116909},
{"learn":[0.4809296151],"iteration":196,"passed_time":0.3335501825,"remaining_time":1.359597952},
{"learn":[0.4802409464],"iteration":197,"passed_time":0.3350843855,"remaining_time":1.357260996},
{"learn":[0.4801644289],"iteration":198,"passed_time":0.3355943383,"remaining_time":1.350809372},
{"learn":[0.4795631428],"iteration":199,"passed_time":0.3371084977,"remaining_time":1.348433991},
{"learn":[0.4787971479],"iteration":200,"passed_time":0.3386094234,"remaining_time":1.346014573},
{"learn":[0.4780209874],"iteration":201,"passed_time":0.3401876326,"remaining_time":1.343909559},
{"learn":[0.4773781757],"iteration":202,"passed_time":0.3418655318,"remaining_time":1.342201127},
{"learn":[0.4765127383],"iteration":203,"passed_time":0.3435770053,"remaining_time":1.340624001},
{"learn":[0.4756541132],"iteration":204,"passed_time":0.3452968059,"remaining_time":1.339077857},
{"learn":[0.4747108205],"iteration":205,"passed_time":0.3469156101,"remaining_time":1.33714075},
{"learn":[0.4738515992],"iteration":206,"passed_time":0.3487010524,"remaining_time":1.335845094},
{"learn":[0.4729686941],"iteration":207,"passed_time":0.3502565401,"remaining_time":1.333669133},
{"learn":[0.4729294506],"iteration":208,"passed_time":0.3509025645,"remaining_time":1.328057074},
{"learn":[0.4720349956],"iteration":209,"passed_time":0.3527248286,"remaining_time":1.326917212},
{"learn":[0.4712728953],"iteration":210,"passed_time":0.35432438,"remaining_time":1.324938084},
{"learn":[0.4705396854],"iteration":211,"passed_time":0.3559824815,"remaining_time":1.323180167},
{"learn":[0.4696762727],"iteration":212,"passed_time":0.3577856923,"remaining_time":1.321959342},
{"learn":[0.46879257],"iteration":213,"passed_time":0.3593658068,"remaining_time":1.319913664},
{"learn":[0.4685887849],"iteration":214,"passed_time":0.3604105526,"remaining_time":1.315917599},
{"learn":[0.4676806976],"iteration":215,"passed_time":0.3621349901,"remaining_time":1.31441589},
{"learn":[0.4666627453],"iteration":216,"passed_time":0.363678168,"remaining_time":1.31225809},
{"learn":[0.4658825624],"iteration":217,"passed_time":0.3654131021,"remaining_time":1.310793788},
{"learn":[0.465615602],"iteration":218,"passed_time":0.3663080779,"remaining_time":1.306331547},
{"learn":[0.4648298538],"iteration":219,"passed_time":0.3679982048,"remaining_time":1.304720908},
{"learn":[0.464173987],"iteration":220,"passed_time":0.3695658865,"remaining_time":1.302677944},
{"learn":[0.4633770036],"iteration":221,"passed_time":0.3712884872,"remaining_time":1.301182176},
{"learn":[0.4626155464],"iteration":222,"passed_time":0.3730515678,"remaining_time":1.299825418},
{"learn":[0.4619064984],"iteration":223,"passed_time":0.3747543544,"remaining_time":1.298256156},
{"learn":[0.4612241348],"iteration":224,"passed_time":0.3763186193,"remaining_time":1.296208577},
{"learn":[0.4604285948],"iteration":225,"passed_time":0.3780934493,"remaining_time":1.294886415},
{"learn":[0.4593282411],"iteration":226,"passed_time":0.3799010018,"remaining_time":1.293671694},
{"learn":[0.4585200299],"iteration":227,"passed_time":0.3815331699,"remaining_time":1.291857926},
{"learn":[0.4577401584],"iteration":228,"passed_time":0.383108879,"remaining_time":1.289855658},
{"learn":[0.4569886195],"iteration":229,"passed_time":0.3847057834,"remaining_time":1.287928057},
{"learn":[0.4564884898],"iteration":230,"passed_time":0.3858343558,"remaining_time":1.284444241},
{"learn":[0.4556810258],"iteration":231,"passed_time":0.3875398357,"remaining_time":1.282890491},
{"learn":[0.4548779414],"iteration":232,"passed_time":0.3891823628,"remaining_time":1.281128207},
{"learn":[0.4540610293],"iteration":233,"passed_time":0.3908540779,"remaining_time":1.279462494},
{"learn":[0.4533137394],"iteration":234,"passed_time":0.3927144275,"remaining_time":1.278410796},
{"learn":[0.4524830509],"iteration":235,"passed_time":0.3942359991,"remaining_time":1.276255523},
{"learn":[0.4517301139],"iteration":236,"passed_time":0.3959151193,"remaining_time":1.27461281},
{"learn":[0.4509232436],"iteration":237,"passed_time":0.3975664672,"remaining_time":1.272880874},
{"learn":[0.45009971],"iteration":238,"passed_time":0.399262678,"remaining_time":1.27129246},
{"learn":[0.4494622078],"iteration":239,"passed_time":0.4009171521,"remaining_time":1.269570982},
{"learn":[0.4486825247],"iteration":240,"passed_time":0.4024997833,"remaining_time":1.267623799},
{"learn":[0.4479631772],"iteration":241,"passed_time":0.4041497654,"remaining_time":1.265890588},
{"learn":[0.4472185942],"iteration":242,"passed_time":0.4057543855,"remaining_time":1.264016748},
{"learn":[0.4465423788],"iteration":243,"passed_time":0.4072213232,"remaining_time":1.261718526},
{"learn":[0.445845095],"iteration":244,"passed_time":0.4089177917,"remaining_time":1.260134419},
{"learn":[0.4449257074],"iteration":245,"passed_time":0.4108664372,"remaining_time":1.259322332},
{"learn":[0.4442658828],"iteration":246,"passed_time":0.4140041332,"remaining_time":1.262125961},
{"learn":[0.4440991589],"iteration":247,"passed_time":0.4151741533,"remaining_time":1.258915175},
{"learn":[0.4433013998],"iteration":248,"passed_time":0.4176765547,"remaining_time":1.259739328},
{"learn":[0.4426234199],"iteration":249,"passed_time":0.4199442006,"remaining_time":1.259832602},
{"learn":[0.4424662673],"iteration":250,"passed_time":0.4209797345,"remaining_time":1.256230363},
{"learn":[0.4417327088],"iteration":251,"passed_time":0.423480771,"remaining_time":1.256998479},
{"learn":[0.4409507359],"iteration":252,"passed_time":0.4255091967,"remaining_time":1.256345336},
{"learn":[0.4402645012],"iteration":253,"passed_time":0.4272955246,"remaining_time":1.25497032},
{"learn":[0.4394453327],"iteration":254,"passed_time":0.429739129,"remaining_time":1.255512357},
{"learn":[0.4386879102],"iteration":255,"passed_time":0.4326237998,"remaining_time":1.257312918},
{"learn":[0.4378677278],"iteration":256,"passed_time":0.4347164694,"remaining_time":1.256787303},
{"learn":[0.4374047642],"iteration":257,"passed_time":0.4365989511,"remaining_time":1.255645045},
{"learn":[0.4365727911],"iteration":258,"passed_time":0.4388485433,"remaining_time":1.255547377},
{"learn":[0.4359208061],"iteration":259,"passed_time":0.4409381259,"remaining_time":1.254977743},
{"learn":[0.4350728128],"iteration":260,"passed_time":0.443142417,"remaining_time":1.25472125},
{"learn":[0.4343518588],"iteration":261,"passed_time":0.4456857951,"remaining_time":1.255405026},
{"learn":[0.4336621854],"iteration":262,"passed_time":0.4478533055,"remaining_time":1.255010974},
{"learn":[0.4328559124],"iteration":263,"passed_time":0.449869241,"remaining_time":1.254180914},
{"learn":[0.4320163969],"iteration":264,"passed_time":0.4519997374,"remaining_time":1.253659649},
{"learn":[0.4313826554],"iteration":265,"passed_time":0.4539461551,"remaining_time":1.252618338},
{"learn":[0.4307037164],"iteration":266,"passed_time":0.455911103,"remaining_time":1.251621118},
{"learn":[0.4299891107],"iteration":267,"passed_time":0.4585585937,"remaining_time":1.252480935},
{"learn":[0.4299281707],"iteration":268,"passed_time":0.4596260237,"remaining_time":1.249020904},
{"learn":[0.4290710993],"iteration":269,"passed_time":0.462399586,"remaining_time":1.250191473},
{"learn":[0.4282890057],"iteration":270,"passed_time":0.4644776834,"remaining_time":1.249462108},
{"learn":[0.4277019889],"iteration":271,"passed_time":0.4667246697,"remaining_time":1.249174851},
{"learn":[0.4270516506],"iteration":272,"passed_time":0.4690478999,"remaining_time":1.249076276,,
{"learn":[0.4266874221],"iteration":273,"passed_time":0.4709601081,"remaining_time":1.247872403},
{"learn":[0.4259151578],"iteration":274,"passed_time":0.4734285151,"remaining_time":1.24812972,
,
{"learn":[0.4251640647],"iteration":275,"passed_time":0.4769164014,"remaining_time":1.251041575},
{"learn":[0.4244527886],"iteration":276,"passed_time":0.4803172273,"remaining_time":1.253679983},
{"learn":[0.4237585407],"iteration":277,"passed_time":0.4823545669,"remaining_time":1.252733803},
{"learn":[0.4230522311],"iteration":278,"passed_time":0.4847015911,"remaining_time":1.252580097},
{"learn":[0.4223435605],"iteration":279,"passed_time":0.4871357622,"remaining_time":1.252634817},
{"learn":[0.421613781],"iteration":280,"passed_time":0.4893858017,"remaining_time":1.252200681},
{"learn":[0.4209416129],"iteration":281,"passed_time":0.4918754788,"remaining_time":1.252363808},
{"learn":[0.4203240405],"iteration":282,"passed_time":0.4939881693,"remaining_time":1.251553065},
{"learn":[0.4196115682],"iteration":283,"passed_time":0.4964937488,"remaining_time":1.251723677},
{"learn":[0.418848015],"iteration":284,"passed_time":0.4988302619,"remaining_time":1.251451359},
{"learn":[0.4181502733],"iteration":285,"passed_time":0.5012004241,"remaining_time":1.251248611},
{"learn":[0.4174690492],"iteration":286,"passed_time":0.5034517183,"remaining_time":1.250735453},
{"learn":[0.4167997839],"iteration":287,"passed_time":0.5061128773,"remaining_time":1.251223502},
{"learn":[0.4161341541],"iteration":288,"passed_time":0.5084640163,"remaining_time":1.250927043},
{"learn":[0.4154357508],"iteration":289,"passed_time":0.5112464286,"remaining_time":1.251672291},
{"learn":[0.4147367294],"iteration":290,"passed_time":0.5138420143,"remaining_time":1.251938104},
{"learn":[0.41398214],"iteration":291,"passed_time":0.5162696724,"remaining_time":1.251777151},
{"learn":[0.4131729163],"iteration":292,"passed_time":0.5188762065,"remaining_time":1.252032348},
{"learn":[0.4123780261],"iteration":293,"passed_time":0.5213664731,"remaining_time":1.251988878},
{"learn":[0.4115668479],"iteration":294,"passed_time":0.5237577304,"remaining_time":1.251692203},
{"learn":[0.4107435658],"iteration":295,"passed_time":0.5265514257,"remaining_time":1.252338526},
{"learn":[0.410072791],"iteration":296,"passed_time":0.5290932256,"remaining_time":1.252365446},
{"learn":[0.4095373819],"iteration":297,"passed_time":0.5312967887,"remaining_time":1.251578341},
{"learn":[0.4088758199],"iteration":298,"passed_time":0.5337426072,"remaining_time":1.251349725},
{"learn":[0.4081725436],"iteration":299,"passed_time":0.535975332,"remaining_time":1.250609108},
{"learn":[0.4075450179],"iteration":300,"passed_time":0.5382705003,"remaining_time":1.250003587},
{"learn":[0.4068869902],"iteration":301,"passed_time":0.5400584875,"remaining_time":1.24821465},
{"learn":[0.4061129458],"iteration":302,"passed_time":0.5423905979,"remaining_time":1.247677382},
{"learn":[0.4053273734],"iteration":303,"passed_time":0.5445028355,"remaining_time":1.246624913},
{"learn":[0.4046606679],"iteration":304,"passed_time":0.5464469781,"remaining_time":1.245182458},
{"learn":[0.4038897987],"iteration":305,"passed_time":0.5485857451,"remaining_time":1.244178128},
{"learn":[0.4033162856],"iteration":306,"passed_time":0.5526963875,"remaining_time":1.247617578},
{"learn":[0.4025966906],"iteration":307,"passed_time":0.555115314,"remaining_time":1.247207134},
{"learn":[0.4019118576],"iteration":308,"passed_time":0.5578305895,"remaining_time":1.247446399},
{"learn":[0.4014877143],"iteration":309,"passed_time":0.5599620818,"remaining_time":1.246367214},
{"learn":[0.4009919626],"iteration":310,"passed_time":0.5618194318,"remaining_time":1.244673918},
{"learn":[0.4002458351],"iteration":311,"passed_time":0.563969192,"remaining_time":1.243624372},
{"learn":[0.3995436828],"iteration":312,"passed_time":0.5661307516,"remaining_time":1.242593694},
{"learn":[0.3989068948],"iteration":313,"passed_time":0.5682733682,"remaining_time":1.241514429},
{"learn":[0.3982253938],"iteration":314,"passed_time":0.5704990616,"remaining_time":1.24060907},
{"learn":[0.3976519391],"iteration":315,"passed_time":0.5721491285,"remaining_time":1.238449379},
{"learn":[0.3975149294],"iteration":316,"passed_time":0.5744136974,"remaining_time":1.237616894},
{"learn":[0.3969259816],"iteration":317,"passed_time":0.5768861991,"remaining_time":1.237221345},
{"learn":[0.3966535866],"iteration":318,"passed_time":0.5783458538,"remaining_time":1.234650553},
{"learn":[0.395903645],"iteration":319,"passed_time":0.5807361399,"remaining_time":1.234064297},
{"learn":[0.3951314677],"iteration":320,"passed_time":0.5826178771,"remaining_time":1.232391086},
{"learn":[0.3943258374],"iteration":321,"passed_time":0.5847606259,"remaining_time":1.231266163},
{"learn":[0.3936249057],"iteration":322,"passed_time":0.5873166198,"remaining_time":1.231001089},
{"learn":[0.3928908139],"iteration":323,"passed_time":0.5894790815,"remaining_time":1.2299008},
{"learn":[0.3921690408],"iteration":324,"passed_time":0.5913149647,"remaining_time":1.228115696},
{"learn":[0.3914544026],"iteration":325,"passed_time":0.5930299872,"remaining_time":1.226080403},
{"learn":[0.390665319],"iteration":326,"passed_time":0.5948722548,"remaining_time":1.224308953},
{"learn":[0.3899229523],"iteration":327,"passed_time":0.5967897606,"remaining_time":1.222691217},
{"learn":[0.3892714471],"iteration":328,"passed_time":0.5986758404,"remaining_time":1.221007565},
{"learn":[0.3887691933],"iteration":329,"passed_time":0.6004326705,"remaining_time":1.21906027},
{"learn":[0.3879976381],"iteration":330,"passed_time":0.6032658992,"remaining_time":1.219289687},
{"learn":[0.3874482988],"iteration":331,"passed_time":0.6060634012,"remaining_time":1.219428771},
{"learn":[0.3869782581],"iteration":332,"passed_time":0.6075564454,"remaining_time":1.216937385},
{"learn":[0.3862479067],"iteration":333,"passed_time":0.6093556417,"remaining_time":1.215062447},
{"learn":[0.3856359332],"iteration":334,"passed_time":0.6112880312,"remaining_time":1.21345236},
{"learn":[0.3849536233],"iteration":335,"passed_time":0.6140261585,"remaining_time":1.213432647},
{"learn":[0.384341105],"iteration":336,"passed_time":0.6191708306,"remaining_time":1.218131337},
{"learn":[0.3836349055],"iteration":337,"passed_time":0.6214779196,"remaining_time":1.21721415},
{"learn":[0.383062402],"iteration":338,"passed_time":0.6239984594,"remaining_time":1.216704961},
{"learn":[0.3824207459],"iteration":339,"passed_time":0.6259271296,"remaining_time":1.215035016},
{"learn":[0.3818387775],"iteration":340,"passed_time":0.6278385014,"remaining_time":1.213330124},
{"learn":[0.381395151],"iteration":341,"passed_time":0.6294515479,"remaining_time":1.211050054},
{"learn":[0.3805541553],"iteration":342,"passed_time":0.6315127652,"remaining_time":1.209632323},
{"learn":[0.3801299747],"iteration":343,"passed_time":0.6333045656,"remaining_time":1.207697079},
{"learn":[0.3795374516],"iteration":344,"passed_time":0.6357287167,"remaining_time":1.206963216},
{"learn":[0.3794732564],"iteration":345,"passed_time":0.6366956394,"remaining_time":1.203465168},
{"learn":[0.3787827143],"iteration":346,"passed_time":0.6385707134,"remaining_time":1.201690708},
{"learn":[0.3782021275],"iteration":347,"passed_time":0.6403535407,"remaining_time":1.199742841},
{"learn":[0.3775771492],"iteration":348,"passed_time":0.642458018,"remaining_time":1.198395902},
{"learn":[0.3768341188],"iteration":349,"passed_time":0.6444711171,"remaining_time":1.196874932},
{"learn":[0.3764799934],"iteration":350,"passed_time":0.6458356222,"remaining_time":1.194151905},
{"learn":[0.3759475849],"iteration":351,"passed_time":0.6474099709,"remaining_time":1.191822901},
{"learn":[0.3753897429],"iteration":352,"passed_time":0.6492471379,"remaining_time":1.189979882},
{"learn":[0.3747847426],"iteration":353,"passed_time":0.6504214523,"remaining_time":1.186927283},
{"learn":[0.3742059603],"iteration":354,"passed_time":0.6523087686,"remaining_time":1.18518072},
{"learn":[0.3736089413],"iteration":355,"passed_time":0.6543740223,"remaining_time":1.183755254},
{"learn":[0.3731540808],"iteration":356,"passed_time":0.6574364129,"remaining_time":1.184122167},
{"learn":[0.3724873769],"iteration":357,"passed_time":0.6593473382,"remaining_time":1.182405003},
{"learn":[0.3718835229],"iteration":358,"passed_time":0.6613866477,"remaining_time":1.180915992},
{"learn":[0.3714611592],"iteration":359,"passed_time":0.6635567321,"remaining_time":1.179656413},
{"learn":[0.3711104186],"iteration":360,"passed_time":0.6649565392,"remaining_time":1.177028334},
{"learn":[0.3704472116],"iteration":361,"passed_time":0.6669573695,"remaining_time":1.175466303},
{"learn":[0.3699009516],"iteration":362,"passed_time":0.6687448938,"remaining_time":1.173527541},
{"learn":[0.3693435736],"iteration":363,"passed_time":0.6706789179,"remaining_time":1.171845582},
{"learn":[0.3687591242],"iteration":364,"passed_time":0.672465358,"remaining_time":1.169905486},
{"learn":[0.3682486252],"iteration":365,"passed_time":0.6744005748,"remaining_time":1.168223946},
{"learn":[0.3676840122],"iteration":366,"passed_time":0.6763089279,"remaining_time":1.16649469},
{"learn":[0.3671307869],"iteration":367,"passed_time":0.6782782384,"remaining_time":1.164869149},
{"learn":[0.3666265351],"iteration":368,"passed_time":0.6802733375,"remaining_time":1.163285843},
{"learn":[0.3659799082],"iteration":369,"passed_time":0.6820026252,"remaining_time":1.161247713},
{"learn":[0.3654436757],"iteration":370,"passed_time":0.6838980207,"remaining_time":1.159492871},
{"learn":[0.3648064177],"iteration":371,"passed_time":0.685611455,"remaining_time":1.157430091},
{"learn":[0.3641903755],"iteration":372,"passed_time":0.6874109074,"remaini,
{"learn":[0.3638174,
{"learn":[0.3637823469],"iteration":373,"passed_time":0.6893096559,"remaining_time":1.15376429},
{"learn":[0.3633092511],"iteration":374,"passed_time":0.6912140637,"remaining_time":1.15202344},
{"learn":[0.3626517628],"iteration":375,"passed_time":0.6933523168,"remaining_time":1.150669802},
{"learn":[0.3620501769],"iteration":376,"passed_time":0.6954453728,"remaining_time":1.149237314},
{"learn":[0.3613407221],"iteration":377,"passed_time":0.6975627485,"remaining_time":1.147841348},
{"learn":[0.3607142884],"iteration":378,"passed_time":0.6996987028,"remaining_time":1.146472017},
{"learn":[0.3600378723],"iteration":379,"passed_time":0.7017584376,"remaining_time":1.144974293},
{"learn":[0.3596143848],"iteration":380,"passed_time":0.7037757335,"remaining_time":1.143404669},
{"learn":[0.3590755163],"iteration":381,"passed_time":0.7058908595,"remaining_time":1.141990972},
{"learn":[0.3585320511],"iteration":382,"passed_time":0.7077201295,"remaining_time":1.140113107},
{"learn":[0.3579289305],"iteration":383,"passed_time":0.7096410876,"remaining_time":1.138382578},
{"learn":[0.3573641321],"iteration":384,"passed_time":0.7132413736,"remaining_time":1.139333623},
{"learn":[0.3568311094],"iteration":385,"passed_time":0.7152437237,"remaining_time":1.137719291},
{"learn":[0.3563254586],"iteration":386,"passed_time":0.7172949565,"remaining_time":1.136180383},
{"learn":[0.3558371247],"iteration":387,"passed_time":0.7197713771,"remaining_time":1.135309492},
{"learn":[0.3554118378],"iteration":388,"passed_time":0.7215387311,"remaining_time":1.133316619},
{"learn":[0.3549028526],"iteration":389,"passed_time":0.7237308192,"remaining_time":1.13198923},
{"learn":[0.3543069861],"iteration":390,"passed_time":0.7255720408,"remaining_time":1.130110928},
{"learn":[0.3537701462],"iteration":391,"passed_time":0.7277307667,"remaining_time":1.128725271},
{"learn":[0.3532187012],"iteration":392,"passed_time":0.7296803334,"remaining_time":1.127012627},
{"learn":[0.3526928811],"iteration":393,"passed_time":0.7317306341,"remaining_time":1.125453716},
{"learn":[0.3520832074],"iteration":394,"passed_time":0.7335772827,"remaining_time":1.123580395},
{"learn":[0.3516311522],"iteration":395,"passed_time":0.7354551867,"remaining_time":1.121754881},
{"learn":[0.3511190481],"iteration":396,"passed_time":0.7376036757,"remaining_time":1.120340092},
{"learn":[0.3505682556],"iteration":397,"passed_time":0.7396511829,"remaining_time":1.118768875},
{"learn":[0.3499650305],"iteration":398,"passed_time":0.7416834126,"remaining_time":1.117172258},
{"learn":[0.3498681497],"iteration":399,"passed_time":0.7427662712,"remaining_time":1.114149407},
{"learn":[0.3494118471],"iteration":400,"passed_time":0.7446743191,"remaining_time":1.112368871},
{"learn":[0.349326595],"iteration":401,"passed_time":0.7453704318,"remaining_time":1.108784871},
{"learn":[0.3488351193],"iteration":402,"passed_time":0.746911986,"remaining_time":1.106467632},
{"learn":[0.3484927164],"iteration":403,"passed_time":0.7482043419,"remaining_time":1.103786603},
{"learn":[0.3480553724],"iteration":404,"passed_time":0.7499928667,"remaining_time":1.101841372},
{"learn":[0.3474250944],"iteration":405,"passed_time":0.7517038819,"remaining_time":1.099783512},
{"learn":[0.3468578968],"iteration":406,"passed_time":0.753245982,"remaining_time":1.097481246},
{"learn":[0.3464036895],"iteration":407,"passed_time":0.7549553353,"remaining_time":1.095425388},
{"learn":[0.3457827103],"iteration":408,"passed_time":0.7568019874,"remaining_time":1.09356962},
{"learn":[0.3452729502],"iteration":409,"passed_time":0.7585299985,"remaining_time":1.091543169},
{"learn":[0.3446985533],"iteration":410,"passed_time":0.7602966737,"remaining_time":1.089573579},
{"learn":[0.3441361108],"iteration":411,"passed_time":0.7618742014,"remaining_time":1.087335025},
{"learn":[0.3435037572],"iteration":412,"passed_time":0.7635912649,"remaining_time":1.085297996},
{"learn":[0.343080599],"iteration":413,"passed_time":0.7651552756,"remaining_time":1.083045873},
{"learn":[0.3425768151],"iteration":414,"passed_time":0.7667536925,"remaining_time":1.080845567},
{"learn":[0.3419376646],"iteration":415,"passed_time":0.7684346751,"remaining_time":1.078764063},
{"learn":[0.3413412124],"iteration":416,"passed_time":0.7702075598,"remaining_time":1.076812967},
{"learn":[0.3412721469],"iteration":417,"passed_time":0.77088656,"remaining_time":1.07333966},
{"learn":[0.3407452912],"iteration":418,"passed_time":0.7725829329,"remaining_time":1.071290415},
{"learn":[0.3403438984],"iteration":419,"passed_time":0.7742566617,"remaining_time":1.06921158},
{"learn":[0.3399220233],"iteration":420,"passed_time":0.7757322489,"remaining_time":1.066862167},
{"learn":[0.3394237767],"iteration":421,"passed_time":0.7773798557,"remaining_time":1.064752504},
{"learn":[0.3389750305],"iteration":422,"passed_time":0.7788689026,"remaining_time":1.062428739},
{"learn":[0.3385361277],"iteration":423,"passed_time":0.7803589007,"remaining_time":1.060110205},
{"learn":[0.338074285],"iteration":424,"passed_time":0.7819552439,"remaining_time":1.057939448},
{"learn":[0.3375846406],"iteration":425,"passed_time":0.7837452457,"remaining_time":1.056032326},
{"learn":[0.3370760739],"iteration":426,"passed_time":0.7854468176,"remaining_time":1.054007088},
{"learn":[0.3364954155],"iteration":427,"passed_time":0.7869608084,"remaining_time":1.051732669},
{"learn":[0.3359301456],"iteration":428,"passed_time":0.7886044516,"remaining_time":1.049634363},
{"learn":[0.3356180539],"iteration":429,"passed_time":0.7899335036,"remaining_time":1.047121156},
{"learn":[0.3350821748],"iteration":430,"passed_time":0.7917836737,"remaining_time":1.045301416},
{"learn":[0.3348611358],"iteration":431,"passed_time":0.7927032919,"remaining_time":1.042258032},
{"learn":[0.3343626838],"iteration":432,"passed_time":0.7943131767,"remaining_time":1.04012834},
{"learn":[0.3338229729],"iteration":433,"passed_time":0.7959373029,"remaining_time":1.038019616},
{"learn":[0.3333229128],"iteration":434,"passed_time":0.7976687608,"remaining_time":1.036052528},
{"learn":[0.3328024929],"iteration":435,"passed_time":0.7993221407,"remaining_time":1.033985521},
{"learn":[0.3322668029],"iteration":436,"passed_time":0.8010534283,"remaining_time":1.032020778},
{"learn":[0.3318970271],"iteration":437,"passed_time":0.8026049598,"remaining_time":1.029826455},
{"learn":[0.331360869],"iteration":438,"passed_time":0.8044872483,"remaining_time":1.028057736},
{"learn":[0.3309412242],"iteration":439,"passed_time":0.8064605579,"remaining_time":1.026404346},
{"learn":[0.330334072],"iteration":440,"passed_time":0.8081759002,"remaining_time":1.024422513},
{"learn":[0.3297699961],"iteration":441,"passed_time":0.8097966169,"remaining_time":1.022322426},
{"learn":[0.3292202654],"iteration":442,"passed_time":0.8113727596,"remaining_time":1.020168458},
{"learn":[0.3288172768],"iteration":443,"passed_time":0.8126061709,"remaining_time":1.017587908},
{"learn":[0.3283884354],"iteration":444,"passed_time":0.8142835097,"remaining_time":1.015567074},
{"learn":[0.3279502899],"iteration":445,"passed_time":0.8156423656,"remaining_time":1.013152176},
{"learn":[0.3275276915],"iteration":446,"passed_time":0.8173175705,"remaining_time":1.01113337},
{"learn":[0.327083274],"iteration":447,"passed_time":0.8188642199,"remaining_time":1.0089577},
{"learn":[0.3265573109],"iteration":448,"passed_time":0.8207340237,"remaining_time":1.007181397},
{"learn":[0.326139547],"iteration":449,"passed_time":0.8221828575,"remaining_time":1.004890159},
{"learn":[0.3257516355],"iteration":450,"passed_time":0.8236248504,"remaining_time":1.00259433},
{"learn":[0.3253221921],"iteration":451,"passed_time":0.8251368439,"remaining_time":1.000387147},
{"learn":[0.3248257242],"iteration":452,"passed_time":0.8267026996,"remaining_time":0.9982480722},
{"learn":[0.3243634004],"iteration":453,"passed_time":0.828213844,"remaining_time":0.9960457242},
{"learn":[0.323865747],"iteration":454,"passed_time":0.8298627382,"remaining_time":0.9940114117},
{"learn":[0.3232929109],"iteration":455,"passed_time":0.8313686771,"remaining_time":0.9918082463},
{"learn":[0.3226650471],"iteration":456,"passed_time":0.8330579484,"remaining_time":0.989825965},
{"learn":[0.3221155207],"iteration":457,"passed_time":0.834656707,"remaining_time":0.9877378498},
{"learn":[0.3215675352],"iteration":458,"passed_time":0.8361182342,"remaining_time":0.9854901192},
{"learn":[0.3211300079],"iteration":459,"passed_time":0.8378159975,"remaining_time":0.9835231275},
{"learn":[0.3206829578],"iteration":460,"passed_time":0.8397239661,"remaining_time":0.9818030754},
{"learn":[0.320159354],"iteration":461,"passed_time":0.8413945806,"remaining_time":0.9798058103},
{"learn":[0.3196375783],"iteration":462,"passed_time":0.8429541275,"remaining_time":0.9776811371},
{"learn":[0.3192093168],"iteration":463,"passed_time":0.8446733832,"remaining_time":0.975743391},
{"learn":[0.318778074],"iteration":464,"passed_time":0.8463973178,"remaining_time":0.9738119678},
{"learn":[0.3187135293],"iteration":465,"passed_time":0.8474086595,"remaining_time":0.9710648588},
{"learn":[0.3181946155],"iteration":466,"passed_time":0.8490600321,"remaining_time":0.9690556684},
{"learn":[0.3177582951],"iteration":467,"passed_time":0.8507350712,"remaining_time":0.96707491},
{"learn":[0.3173441645],"iteration":468,"passed_time":0.8525534009,"remaining_time":0.9652576884},
{"learn":[0.3168130291],"iteration":469,"passed_time":0.8541716282,"remaining_time":0.9632148148},
{"learn":[0.316314776],"iteration":470,"passed_time":0.8557461291,"remaining_time":0.9611246333},
{"learn":[0.3158038635],"iteration":471,"passed_time":0.8574115672,"remaining_time":0.9591383633},
{"learn":[0.3154024533],"iteration":472,"passed_time":0.859063071,"remaining_time":0.9571379248},
{"learn":[0.3149940897],"iteration":473,"passed_time":0.860694758,"remaining_time":0.9551169678},
{"learn":[0.3144152225],"iteration":474,"passed_time":0.8623657424,"remaining_time":0.9531410837},
{"learn":[0.3143696763],"iteration":475,"passed_time":0.8629475028,"remaining_time":0.949967419},
{"learn":[0.3138759963],"iteration":476,"passed_time":0.8645660436,"remaining_time":0.9479413853},
{"learn":[0.3134879666],"iteration":477,"passed_time":0.8663796335,"remaining_time":0.94613006},
{"learn":[0.3129558207],"iteration":478,"passed_time":0.8683726159,"remaining_time":0.9445138474},
{"learn":[0.3125054592],"iteration":479,"passed_time":0.8700012733,"remaining_time":0.9425013794},
{"learn":[0.3122005174],"iteration":480,"passed_time":0.8712363656,"remaining_time":0.9400658498},
{"learn":[0.3116757717],"iteration":481,"passed_time":0.8730055447,"remaining_time":0.9382092783},
{"learn":[0.3111516879],"iteration":482,"passed_time":0.8747564295,"remaining_time":0.9363334867},
{"learn":[0.3106657378],"iteration":483,"passed_time":0.8765212833,"remaining_time":0.9344731037},
{"learn":[0.3102159029],"iteration":484,"passed_time":0.8783322463,"remaining_time":0.932662076},
{"learn":[0.3097096327],"iteration":485,"passed_time":0.8799942986,"remaining_time":0.9306935586},
{"learn":[0.3092176318],"iteration":486,"passed_time":0.8815022566,"remaining_time":0.9285639787},
{"learn":[0.3091383258],"iteration":487,"passed_time":0.8821463238,"remaining_time":0.9255305693},
{"learn":[0.3086231168],"iteration":488,"passed_time":0.8837062489,"remaining_time":0.9234639942},
{"learn":[0.3081379671],"iteration":489,"passed_time":0.8852781566,"remaining_time":0.9214119589},
{"learn":[0.3077142811],"iteration":490,"passed_time":0.8870349156,"remaining_time":0.9195535072},
{"learn":[0.3072833396],"iteration":491,"passed_time":0.8888283688,"remaining_time":0.9177333565},
{"learn":[0.3072400329],"iteration":492,"passed_time":0.8893881311,"remaining_time":0.9146445892},
{"learn":[0.3068424472],"iteration":493,"passed_time":0.8908852801,"remaining_time":0.912526218},
{"learn":[0.3063858889],"iteration":494,"passed_time":0.8926062123,"remaining_time":0.9106386611},
{"learn":[0.3059879322],"iteration":495,"passed_time":0.8943430726,"remaining_time":0.9087679609},
{"learn":[0.305585306],"iteration":496,"passed_time":0.8959012828,"remaining_time":0.9067169925},
{"learn":[0.3051022147],"iteration":497,"passed_time":0.8977416052,"remaining_time":0.9049523811},
{"learn":[0.3050323901],"iteration":498,"passed_time":0.8984187238,"remaining_time":0.9020196005},
{"learn":[0.3045790228],"iteration":499,"passed_time":0.9000425375,"remaining_time":0.9000425375},
{"learn":[0.3041102811],"iteration":500,"passed_time":0.9016929543,"remaining_time":0.8980933816},
{"learn":[0.3035946594],"iteration":501,"passed_time":0.9032600729,"remaining_time":0.8960627815},
{"learn":[0.3032648027],"iteration":502,"passed_time":0.9047904317,"remaining_time":0.8939977029},
{"learn":[0.3027672005],"iteration":503,"passed_time":0.9064520139,"remaining_time":0.8920638867},
{"learn":[0.3024493697],"iteration":504,"passed_time":0.9077904744,"remaining_time":0.8898144254},
{"learn":[0.3019856325],"iteration":505,"passed_time":0.9094451208,"remaining_time":0.8878772523},
{"learn":[0.3016854877],"iteration":506,"passed_time":0.9105312077,"remaining_time":0.8853883341},
{"learn":[0.3012020166],"iteration":507,"passed_time":0.9121664546,"remaining_time":0.8834368025},
{"learn":[0.3008290096],"iteration":508,"passed_time":0.9133876208,"remaining_time":0.8810870762},
{"learn":[0.3003967928],"iteration":509,"passed_time":0.9151929254,"remaining_time":0.8793030068},
{"learn":[0.3000703535],"iteration":510,"passed_time":0.9169050313,"remaining_time":0.8774296679},
{"learn":[0.2995813741],"iteration":511,"passed_time":0.9185894507,"remaining_time":0.8755305702},
{"learn":[0.2992045466],"iteration":512,"passed_time":0.9204247107,"remaining_time":0.8737755051},
{"learn":[0.298727589],"iteration":513,"passed_time":0.922176493,"remaining_time":0.8719411977},
{"learn":[0.298303044],"iteration":514,"passed_time":0.9240903477,"remaining_time":0.870259842},
{"learn":[0.2978013722],"iteration":515,"passed_time":0.9260630295,"remaining_time":0.8686327641},
{"learn":[0.297466697],"iteration":516,"passed_time":0.9278044137,"remaining_time":0.8667882627},
{"learn":[0.2969777511],"iteration":517,"passed_time":0.9293001321,"remaining_time":0.8647155669},
{"learn":[0.2965829989],"iteration":518,"passed_time":0.9313289104,"remaining_time":0.863139125},
{"learn":[0.2962024052],"iteration":519,"passed_time":0.932922438,"remaining_time":0.8611591736},
{"learn":[0.2957085786],"iteration":520,"passed_time":0.9343434323,"remaining_time":0.8590220807},
{"learn":[0.2952761168],"iteration":521,"passed_time":0.9358707679,"remaining_time":0.8569851093},
{"learn":[0.2948379585],"iteration":522,"passed_time":0.9372964756,"remaining_time":0.8548573974},
{"learn":[0.2943985215],"iteration":523,"passed_time":0.9389379539,"remaining_time":0.8529283703},
{"learn":[0.2940660735],"iteration":524,"passed_time":0.9403931813,"remaining_time":0.8508319259},
{"learn":[0.2936584841],"iteration":525,"passed_time":0.9421264798,"remaining_time":0.8489885008},
{"learn":[0.293325682],"iteration":526,"passed_time":0.9437912756,"remaining_time":0.8470840102},
{"learn":[0.2929444979],"iteration":527,"passed_time":0.9454105572,"remaining_time":0.8451397405},
{"learn":[0.2925680947],"iteration":528,"passed_time":0.9470018088,"remaining_time":0.8431717428},
{"learn":[0.2922082221],"iteration":529,"passed_time":0.9488542823,"remaining_time":0.8414368164},
{"learn":[0.291812073],"iteration":530,"passed_time":0.9505315145,"remaining_time":0.8395466673},
{"learn":[0.2914202531],"iteration":531,"passed_time":0.9521511059,"remaining_time":0.8376066119},
{"learn":[0.2910089645],"iteration":532,"passed_time":0.9537956585,"remaining_time":0.8356896295},
{"learn":[0.2906167009],"iteration":533,"passed_time":0.9554724888,"remaining_time":0.8338018348},
{"learn":[0.2902660249],"iteration":534,"passed_time":0.9570576475,"remaining_time":0.8318351516},
{"learn":[0.2898411729],"iteration":535,"passed_time":0.9587887237,"remaining_time":0.8299962086},
{"learn":[0.2894250545],"iteration":536,"passed_time":0.960260659,"remaining_time":0.8279342368},
{"learn":[0.2890566948],"iteration":537,"passed_time":0.961986415,"remaining_time":0.8260924233},
{"learn":[0.2888612622],"iteration":538,"passed_time":0.9630111353,"remaining_time":0.8236514534},
{"learn":[0.2884768353],"iteration":539,"passed_time":0.9646847702,"remaining_time":0.821768508},
{"learn":[0.2880684783],"iteration":540,"passed_time":0.9662363308,"remaining_time":0.819782765},
{"learn":[0.2877165831],"iteration":541,"passed_time":0.9679368969,"remaining_time":0.8179245365},
{"learn":[0.2873075313],"iteration":542,"passed_time":0.9697609541,"remaining_time":0.8161708214},
{"learn":[0.2869460689],"iteration":543,"passed_time":0.9714883238,"remaining_time":0.8143358008},
{"learn":[0.2865469013],"iteration":544,"passed_time":0.9731574138,"remaining_time":0.8124525198},
{"learn":[0.2861203548],"iteration":545,"passed_time":0.9749027406,"remaining_time":0.8106334143},
{"learn":[0.2856836846],"iteration":546,"passed_time":0.9766517621,"remaining_time":0.8088176384},
{"learn":[0.2853674777],"iteration":547,"passed_time":0.9783200266,"remaining_time":0.8069354964},
{"learn":[0.2850334402],"iteration":548,"passed_time":0.9799730785,"remaining_time":0.8050416364},
{"learn":[0.2846253102],"iteration":549,"passed_time":0.9815850088,"remaining_time":0.8031150072},
{"learn":[0.2842374135],"iteration":550,"passed_time":0.9831372127,"remaining_time":0.8011408503},
{"learn":[0.2839724036],"iteration":551,"passed_time":0.9844606228,"remaining_time":0.7989825344},
{"learn":[0.2835997126],"iteration":552,"passed_time":0.9861627961,"remaining_time":0.7971333994},
{"learn":[0.2833015987],"iteration":553,"passed_time":0.9878896327,"remaining_time":0.7953046501},
{"learn":[0.282869981],"iteration":554,"passed_time":0.9895253953,"remaining_time":0.7934032449},
{"learn":[0.2825618571],"iteration":555,"passed_time":0.9913473405,"remaining_time":0.7916514733},
{"learn":[0.2822224036],"iteration":556,"passed_time":0.9930186073,"remaining_time":0.7897796105},
{"learn":[0.2821852473],"iteration":557,"passed_time":0.9937744692,"remaining_time":0.7871833609},
{"learn":[0.2817151307],"iteration":558,"passed_time":0.9960120532,"remaining_time":0.7857626395},
{"learn":[0.2813781766],"iteration":559,"passed_time":0.9975900994,"remaining_time":0.7838207924},
{"learn":[0.2809764744],"iteration":560,"passed_time":0.9990594297,"remaining_time":0.7817951687},
{"learn":[0.2808186403],"iteration":561,"passed_time":1.000213981,"remaining_time":0.7795261988},
{"learn":[0.2804794426],"iteration":562,"passed_time":1.001996748,"remaining_time":0.7777488081},
{"learn":[0.2801137517],"iteration":563,"passed_time":1.003900186,"remaining_time":0.7760646825},
{"learn":[0.279684416],"iteration":564,"passed_time":1.006071968,"remaining_time":0.7745863828},
{"learn":[0.2792611028],"iteration":565,"passed_time":1.007944394,"remaining_time":0.7728760899},
{"learn":[0.2788502894],"iteration":566,"passed_time":1.00996744,"remaining_time":0.7712802495},
{"learn":[0.2784604591],"iteration":567,"passed_time":1.01169406,"remaining_time":0.7694574538},
{"learn":[0.2780627948],"iteration":568,"passed_time":1.013191258,"remaining_time":0.7674612163},
{"learn":[0.2776466576],"iteration":569,"passed_time":1.015127634,"remaining_time":0.76579804},
{"learn":[0.2772369222],"iteration":570,"passed_time":1.016573782,"remaining_time":0.7637655911},
{"learn":[0.2767840567],"iteration":571,"passed_time":1.01809741,"remaining_time":0.7617931671},
{"learn":[0.2763318949],"iteration":572,"passed_time":1.019688246,"remaining_time":0.759872393},
{"learn":[0.2759737567],"iteration":573,"passed_time":1.021127969,"remaining_time":0.7578406185},
{"learn":[0.275522351],"iteration":574,"passed_time":1.022806832,"remaining_time":0.7559876582},
{"learn":[0.2751439323],"iteration":575,"passed_time":1.024417207,"remaining_time":0.7540848883},
{"learn":[0.2747169284],"iteration":576,"passed_time":1.02603186,"remaining_time":0.752186268},
{"learn":[0.2746982196],"iteration":577,"passed_time":1.026616926,"remaining_time":0.749536925},
{"learn":[0.2746125884],"iteration":578,"passed_time":1.027490848,"remaining_time":0.7471047446},
{"learn":[0.2741833633],"iteration":579,"passed_time":1.029239419,"remaining_time":0.7453113032},
{"learn":[0.2738191662],"iteration":580,"passed_time":1.030932038,"remaining_time":0.7434776657},
{"learn":[0.2734657738],"iteration":581,"passed_time":1.032434782,"remaining_time":0.7415081424},
{"learn":[0.2730327797],"iteration":582,"passed_time":1.034228294,"remaining_time":0.7397481963},
{"learn":[0.2726576914],"iteration":583,"passed_time":1.035977658,"remaining_time":0.7379566877},
{"learn":[0.2722480292],"iteration":584,"passed_time":1.037582874,"remaining_time":0.7360630642},
{"learn":[0.2719888953],"iteration":585,"passed_time":1.038717919,"remaining_time":0.7338382567},
{"learn":[0.2716730791],"iteration":586,"passed_time":1.0403779,"remaining_time":0.7319864953},
{"learn":[0.2712920118],"iteration":587,"passed_time":1.042141044,"remaining_time":0.7302076701},
{"learn":[0.2708621546],"iteration":588,"passed_time":1.043730248,"remaining_time":0.7283075244},
{"learn":[0.2704867254],"iteration":589,"passed_time":1.045244911,"remaining_time":0.7263566332},
{"learn":[0.2703113645],"iteration":590,"passed_time":1.046175026,"remaining_time":0.7240026828},
{"learn":[0.2699446672],"iteration":591,"passed_time":1.047916442,"remaining_time":0.7222126829},
{"learn":[0.2697066178],"iteration":592,"passed_time":1.049041728,"remaining_time":0.7199999716},
{"learn":[0.2693296005],"iteration":593,"passed_time":1.050684809,"remaining_time":0.7181448356},
{"learn":[0.2690687826],"iteration":594,"passed_time":1.051999745,"remaining_time":0.7160670533},
{"learn":[0.2686555791],"iteration":595,"passed_time":1.053687842,"remaining_time":0.7142447787},
{"learn":[0.2683076482],"iteration":596,"passed_time":1.055290124,"remaining_time":0.712365025},
{"learn":[0.2679515204],"iteration":597,"passed_time":1.05692222,"remaining_time":0.7105062416},
{"learn":[0.2676404649],"iteration":598,"passed_time":1.058503769,"remaining_time":0.708614376},
{"learn":[0.2673572594],"iteration":599,"passed_time":1.060149894,"remaining_time":0.7067665959},
{"learn":[0.2670131453],"iteration":600,"passed_time":1.061678879,"remaining_time":0.7048417182},
{"learn":[0.2666194687],"iteration":601,"passed_time":1.06329852,"remaining_time":0.7029780914},
{"learn":[0.2662618424],"iteration":602,"passed_time":1.064931496,"remaining_time":0.7011240532},
{"learn":[0.2659369617],"iteration":603,"passed_time":1.066711799,"remaining_time":0.6993673384},
{"learn":[0.2655977753],"iteration":604,"passed_time":1.068390123,"remaining_time":0.6975439644},
{"learn":[0.2655842177],"iteration":605,"passed_time":1.06896254,"remaining_time":0.6950020475},
{"learn":[0.2651820243],"iteration":606,"passed_time":1.070750973,"remaining_time":0.6932539248},
{"learn":[0.2647573869],"iteration":607,"passed_time":1.072546289,"remaining_time":0.6915101071},
{"learn":[0.2644356625],"iteration":608,"passed_time":1.074502252,"remaining_time":0.6898692622},
{"learn":[0.2640957919],"iteration":609,"passed_time":1.07589825,"remaining_time":0.6878693729},
{"learn":[0.2640825432],"iteration":610,"passed_time":1.076494841,"remaining_time":0.6853625094},
{"learn":[0.2636936776],"iteration":611,"passed_time":1.078294182,"remaining_time":0.6836244163},
{"learn":[0.2633585008],"iteration":612,"passed_time":1.079911248,"remaining_time":0.6817710489},
{"learn":[0.2629702884],"iteration":613,"passed_time":1.081905594,"remaining_time":0.6801556338},
{"learn":[0.2626390231],"iteration":614,"passed_time":1.084000323,"remaining_time":0.6786018285},
{"learn":[0.2623211225],"iteration":615,"passed_time":1.085484906,"remaining_time":0.6766659152},
{"learn":[0.2619748068],"iteration":616,"passed_time":1.08716747,"remaining_time":0.6748543614},
{"learn":[0.2616033171],"iteration":617,"passed_time":1.088814238,"remaining_time":0.6730210988},
{"learn":[0.2612914705],"iteration":618,"passed_time":1.09071013,"remaining_time":0.6713417761},
{"learn":[0.2609508913],"iteration":619,"passed_time":1.092490108,"remaining_time":0.6695907112},
{"learn":[0.2605508232],"iteration":620,"passed_time":1.09429442,"remaining_time":0.6678544046},
{"learn":[0.2602375438],"iteration":621,"passed_time":1.095809572,"remaining_time":0.6659421513},
{"learn":[0.2599302371],"iteration":622,"passed_time":1.09749371,"remaining_time":0.6641334326},
{"learn":[0.259639433],"iteration":623,"passed_time":1.099854676,"remaining_time":0.662732946},
{"learn":[0.2592506582],"iteration":624,"passed_time":1.10211562,"remaining_time":0.6612693718},
{"learn":[0.2588983363],"iteration":625,"passed_time":1.103729792,"remaining_time":0.6594168403},
{"learn":[0.2584638212],"iteration":626,"passed_time":1.105491667,"remaining_time":0.6576529373},
{"learn":[0.2580991501],"iteration":627,"passed_time":1.10711539,"remaining_time":0.6558072057},
{"learn":[0.2580043131],"iteration":628,"passed_time":1.107962537,"remaining_time":0.6535041358},
{"learn":[0.2576615408],"iteration":629,"passed_time":1.109503674,"remaining_time":0.6516132691},
{"learn":[0.2573829708],"iteration":630,"passed_time":1.111201599,"remaining_time":0.6498151982},
{"learn":[0.2570561196],"iteration":631,"passed_time":1.112743393,"remaining_time":0.6479265326},
{"learn":[0.2567293189],"iteration":632,"passed_time":1.114439486,"remaining_time":0.6461284224},
{"learn":[0.2563435453],"iteration":633,"passed_time":1.116264132,"remaining_time":0.6444048459},
{"learn":[0.2559553902],"iteration":634,"passed_time":1.117986591,"remaining_time":0.6426222139},
{"learn":[0.2555982278],"iteration":635,"passed_time":1.119607456,"remaining_time":0.6407816255},
{"learn":[0.2552705763],"iteration":636,"passed_time":1.121382356,"remaining_time":0.6390295058},
{"learn":[0.254948553],"iteration":637,"passed_time":1.123448146,"remaining_time":0.6374423651},
{"learn":[0.2546726974],"iteration":638,"passed_time":1.125152146,"remaining_time":0.6356493342},
{"learn":[0.2543433547],"iteration":639,"passed_time":1.126931808,"remaining_time":0.6338991417},
{"learn":[0.2540807709],"iteration":640,"passed_time":1.128672628,"remaining_time":0.6321271035},
{"learn":[0.2537388331],"iteration":641,"passed_time":1.130616759,"remaining_time":0.6304685355},
{"learn":[0.2533724157],"iteration":642,"passed_time":1.1323527,"remaining_time":0.6286934898},
{"learn":[0.2530001759],"iteration":643,"passed_time":1.133958013,"remaining_time":0.6268463549},
{"learn":[0.2525746902],"iteration":644,"passed_time":1.135564002,"remaining_time":0.6250003424},
{"learn":[0.2523509823],"iteration":645,"passed_time":1.137336929,"remaining_time":0.6232465524},
{"learn":[0.252307175],"iteration":646,"passed_time":1.13796754,"remaining_time":0,
{"learn":[,
{"learn":[0.252276036],"iteration":647,"passed_time":1.138692125,"remaining_time":0.,
{"learn":,
{"learn":[0.2519327522],"iteration":648,"passed_time":1.140449408,"remaining_time":0.,
{"learn":,
{"learn":[0.2516215261],"iteration":649,"passed_time":1.142335542,"remaining_time":0.,
{"learn":,
{"learn":[0.2512665385],"iteration":650,"passed_time":1.144059057,"remaining_time":0.,
{"learn":,
{"learn":[0.2508984525],"iteration":651,"passed_time":1.145556858,"remaining_time":0,
{"learn":[,
{"learn":[0.2505550494],"iteration":652,"passed_time":1.147831616,"remaining_time",
{"learn":[0.,
{"learn":[0.2503155745],"iteration":653,"passed_time":1.148984089,"remaining_time",
{"learn":[0.,
{"learn":[0.2499760634],"iteration":654,"passed_time":1.15065411,"remaining_time":,
{"learn":[,
{"learn":[0.2496991462],"iteration":655,"passed_time":1.152247482,"remaining_time":,
{"learn":[,
{"learn":[0.2494055711],"iteration":656,"passed_time":1.153960821,"remaining_time":0,
{"learn":[,
{"learn":[0.2490952936],"iteration":657,"passed_time":1.155928328,"remaining_time":0,
{"learn":[,
{"learn":[0.2488107805],"iteration":658,"passed_time":1.157462341,"remaining_time":,
{"learn":[0,
{"learn":[0.2484123621],"iteration":659,"passed_time":1.159045747,"remaining_time":,
{"learn":[0,
{"learn":[0.2481092996],"iteration":660,"passed_time":1.160824282,"remaining_time",
{"learn":[0.,
{"learn":[0.2477680203],"iteration":661,"passed_time":1.162461381,"remaining_tim,
{"learn":[0.24,
{"learn":[0.2473990284],"iteration":662,"passed_time":1.164232566,"remaining_tim,
{"learn":[0.24,
{"learn":[0.2470406595],"iteration":663,"passed_time":1.165745222,"remaining_tim,
{"learn":[0.24,
{"learn":[0.2467466858],"iteration":664,"passed_time":1.167374615,"remaining_tim,
{"learn":[0.24,
{"learn":[0.2464222335],"iteration":665,"passed_time":1.169241155,"remaining_tim,
{"learn":[0.24,
{"learn":[0.246090262],"iteration":666,"passed_time":1.170973338,"remaining_time,
{"learn":[0.2,
{"learn":[0.2457723831],"iteration":667,"passed_time":1.172447483,"remaining_time":0.5827134198},
{"learn":[0.2456268693],"iteration":668,"passed_time":1.173579734,"remaining_tim,
{"learn":[0.24,
{"learn":[0.245297926],"iteration":669,"passed_time":1.174962396,"remaining_time,
{"learn":[0.2,
{"learn":[0.2450543171],"iteration":670,"passed_time":1.176705204,"remaining_time,
{"learn":[0.2,
{"learn":[0.2448048356],"iteration":671,"passed_time":1.178753806,"remaining_time,
{"learn":[0.2,
{"learn":[0.2444643622],"iteration":672,"passed_time":1.180266797,"remaining_time,
{"learn":[0.2,
{"learn":[0.2441622145],"iteration":673,"passed_time":1.181849591,"remaining_time,
{"learn":[0.,
{"learn":[0.2440400072],"iteration":674,"passed_time":1.182865226,"remaining_tim,
{"learn":[0.24,
{"learn":[0.243717832],"iteration":675,"passed_time":1.184845833,"remaining_time,
{"learn":[0.2,
{"learn":[0.2433877109],"iteration":676,"passed_time":1.186744958,"remaining_tim,
{"learn":[0.24,
{"learn":[0.2430704877],"iteration":677,"passed_time":1.188424351,"remaining_tim,
{"learn":[0.24,
{"learn":[0.2428579385],"iteration":678,"passed_time":1.189876103,"remaining_tim,
{"learn":[0.24,
{"learn":[0.2424936541],"iteration":679,"passed_time":1.191517842,"remaining_tim,
{"learn":[0.23,
{"learn":[0.2422642299],"iteration":680,"passed_time":1.193358903,"remaining_tim,
{"learn":[0.23,
{"learn":[0.241953703],"iteration":681,"passed_time":1.195413921,"remaining_time,
{"learn":[0.2,
{"learn":[0.2416989022],"iteration":682,"passed_time":1.196913017,"remaining_time,
{"learn":[0.2,
{"learn":[0.2414055157],"iteration":683,"passed_time":1.198590624,"remaining_ti,
{"learn":[0.238,
{"learn":[0.2411138778],"iteration":684,"passed_time":1.200156039,"remaining_ti,
{"learn":[0.238,
{"learn":[0.2407995609],"iteration":685,"passed_time":1.2018286,"remaining_time,
{"learn":[0.2,
{"learn":[0.2404985202],"iteration":686,"passed_time":1.203753473,"remaining_tim,
{"learn":[0.23,
{"learn":[0.2402198843],"iteration":687,"passed_time":1.20545287,"remaining_time":0.5466588598},
{"learn":[0.2398460468],"iteration":688,"passed_time":1.207206275,"remaining_time":0.5449073319},
{"learn":[0.2398057666],"iteration":689,"passed_time":1.207945891,"remaining_time,
{"learn":[0.,
{"learn":[0.2394738432],"iteration":690,"passed_time":1.209857307,"remaining_time":0.5410215743},
{"learn":[0.2391177623],"iteration":691,"passed_time":1.211649452,"remaining_time":0.5392890624},
{"learn":[0.2388283365],"iteration":692,"passed_time":1.213324756,"remaining_time":0.5375046177},
{"learn":[0.2385423805],"iteration":693,"passed_time":1.214981679,"remaining_time":0.5357123831},
{"learn":[0.238324579],"iteration":694,"passed_time":1.216130749,"remaining_time":0.5336976669},
{"learn":[0.2379971398],"iteration":695,"passed_time":1.217828523,"remaining_time":0.5319251022},
{"learn":[0.2376945838],"iteration":696,"passed_time":1.219491858,"remaining_time":0.5301377803},
{"learn":[0.2373972775],"iteration":697,"passed_time":1.221202338,"remaining_time":0.5283712122},
{"learn":[0.2373306616],"iteration":698,"passed_time":1.221988794,"remaining_time":0.5262069056},
{"learn":[0.2369657895],"iteration":699,"passed_time":1.223857797,"remaining_time":0.5245104844},
{"learn":[0.2366519038],"iteration":700,"passed_time":1.225985365,"remaining_time":0.5229238575},
{"learn":[0.2362957789],"iteration":701,"passed_time":1.227653084,"remaining_time":0.5211404832},
{"learn":[0.2360291109],"iteration":702,"passed_time":1.22940127,"remaining_time":0.5193914329},
{"learn":[0.2357324038],"iteration":703,"passed_time":1.231084464,"remaining_time":0.5176150589},
{"learn":[0.2354623943],"iteration":704,"passed_time":1.232601485,"remaining_time":0.5157694156},
{"learn":[0.235150878],"iteration":705,"passed_time":1.234480922,"remaining_time":0.5140756248},
{"learn":[0.2348995415],"iteration":706,"passed_time":1.236482942,"remaining_time":0.5124321102},
{"learn":[0.2345809845],"iteration":707,"passed_time":1.238218984,"remaining_time":0.5106778859},
{"learn":[0.2342845043],"iteration":708,"passed_time":1.240068773,"remaining_time":0.508970399},
{"learn":[0.2340831764],"iteration":709,"passed_time":1.242045147,"remaining_time":0.5073142149},
{"learn":[0.2338051573],"iteration":710,"passed_time":1.243579656,"remaining_time":0.5054775254},
{"learn":[0.2334427691],"iteration":711,"passed_time":1.24506526,"remaining_time":0.5036219027},
{"learn":[0.2333790655],"iteration":712,"passed_time":1.245849175,"remaining_,
{"learn":[0.23107,
{"learn":[0.2331098355],"iteration":713,"passed_time":1.247587856,"remaining_,
{"learn":[0.23075,
{"learn":[0.2328540489],"iteration":714,"passed_time":1.249484455,"remaining_time":0.4980462513},
{"learn":[0.2325026537],"iteration":715,"passed_time":1.251255724,"remaining_time":0.4963081365},
{"learn":[0.2322013855],"iteration":716,"passed_time":1.253026574,"remaining_time":0.4945697633},
{"learn":[0.2318809047],"iteration":717,"passed_time":1.254909803,"remaining_time":0.492875438},
{"learn":[0.2316068231],"iteration":718,"passed_time":1.256847071,"remaining_time":0.4912017065},
{"learn":[0.2313202048],"iteration":719,"passed_time":1.258071823,"remaining_time":0.4892501533},
{"learn":[0.2310289983],"iteration":720,"passed_time":1.259964644,"remaining_time":0.4875591342},
{"learn":[0.2307590623],"iteration":721,"passed_time":1.261599446,"remaining_time":0.4857682076},
{"learn":[0.2304268746],"iteration":722,"passed_time":1.263159786,"remaining_time":0.483949185},
{"learn":[0.2301693703],"iteration":723,"passed_time":1.264986225,"remaining_time":0.4822323178},
{"learn":[0.2298332492],"iteration":724,"passed_time":1.266726919,"remaining_time":0.4804826246},
{"learn":[0.2294980484],"iteration":725,"passed_time":1.268399335,"remaining_time":0.4787071871},
{"learn":[0.2292673407],"iteration":726,"passed_time":1.269949984,"remaining_time":0.4768863075},
{"learn":[0.2289314875],"iteration":727,"passed_time":1.271748357,"remaining_time":0.4751587269},
{"learn":[0.2286287668],"iteration":728,"passed_time":1.273655416,"remaining_time":0.4734713548},
{"learn":[0.2283251119],"iteration":729,"passed_time":1.275296081,"remaining_time":0.471684852},
{"learn":[0.2280199523],"iteration":730,"passed_time":1.276969638,"remaining_time":0.4699108517},
{"learn":[0.2277129231],"iteration":731,"passed_time":1.278966466,"remaining_time":0.4682554822},
{"learn":[0.2274651204],"iteration":732,"passed_time":1.281102602,"remaining_time":0.4666499245},
{"learn":[0.2272135547],"iteration":733,"passed_time":1.282627218,"remaining_time":0.4648213078},
{"learn":[0.226924606],"iteration":734,"passed_time":1.284343174,"remaining_time":0.4630625049},
{"learn":[0.2267199813],"iteration":735,"passed_time":1.286018658,"remaining_time":0.4612893012},
{"learn":[0.2266055578],"iteration":736,"passed_time":1.287020264,"remaining_time":0.4592758879},
{"learn":[0.226316912],"iteration":737,"passed_time":1.288849428,"remaining_time":0.4575590111},
{"learn":[0.2260855085],"iteration":738,"passed_time":1.290544971,"remaining_time":0.4557946379},
{"learn":[0.2258101555],"iteration":739,"passed_time":1.292412695,"remaining_time":0.4540909467},
{"learn":[0.2257197676],"iteration":740,"passed_time":1.293296512,"remaining_time":0.4520429105},
{"learn":[0.2254794996],"iteration":741,"passed_time":1.295083775,"remaining_time":0.4503121482},
{"learn":[0.2252508412],"iteration":742,"passed_time":1.296941512,"remaining_time":0.4486056106},
{"learn":[0.2250043631],"iteration":743,"passed_time":1.298557281,"remaining_time":0.4468154084},
{"learn":[0.2249785748],"iteration":744,"passed_time":1.299321185,"remaining_time":0.444734097},
{"learn":[0.2247448386],"iteration":745,"passed_time":1.300794376,"remaining_time":0.4428978171},
{"learn":[0.2245038253],"iteration":746,"passed_time":1.302329871,"remaining_time":0.441083611},
{"learn":[0.2242348669],"iteration":747,"passed_time":1.304268713,"remaining_time":0.4394060369},
{"learn":[0.2239457744],"iteration":748,"passed_time":1.305985654,"remaining_time":0.4376534034},
{"learn":[0.223730884],"iteration":749,"passed_time":1.307687269,"remaining_time":0.4358957563},
{"learn":[0.223433934],"iteration":750,"passed_time":1.309486898,"remaining_time":0.4341707558},
{"learn":[0.2231795703],"iteration":751,"passed_time":1.311467101,"remaining_time":0.4325051076},
{"learn":[0.2231660186],"iteration":752,"passed_time":1.312264554,"remaining_time":0.4304506572},
{"learn":[0.2229355465],"iteration":753,"passed_time":1.313835891,"remaining_time":0.4286520279},
{"learn":[0.2226717817],"iteration":754,"passed_time":1.315351121,"remaining_time":0.4268357944},
{"learn":[0.2223953669],"iteration":755,"passed_time":1.317052321,"remaining_time":0.4250803786},
{"learn":[0.2220916062],"iteration":756,"passed_time":1.318726518,"remaining_time":0.4233164383},
{"learn":[0.2217956771],"iteration":757,"passed_time":1.320638442,"remaining_time":0.4216286318},
{"learn":[0.2215268555],"iteration":758,"passed_time":1.322698971,"remaining_time":0.4199874204},
{"learn":[0.2212807771],"iteration":759,"passed_time":1.324487006,"remaining_time":0.4182590545},
{"learn":[0.2212674775],"iteration":760,"passed_time":1.325186234,"remaining_time":0.4161885806},
{"learn":[0.2210037567],"iteration":761,"passed_time":1.326822656,"remaining_time":0.4144144254},
{"learn":[0.2207425654],"iteration":762,"passed_time":1.328904522,"remaining_time":0.4127789931},
{"learn":[0.2204705222],"iteration":763,"passed_time":1.330626528,"remaining_time":0.411031231},
{"learn":[0.2201615883],"iteration":764,"passed_time":1.332556042,"remaining_time":0.409347281},
{"learn":[0.2198666413],"iteration":765,"passed_time":1.334364861,"remaining_time":0.407625819},
{"learn":[0.219641159],"iteration":766,"passed_time":1.336046175,"remaining_time":0.405865396},
{"learn":[0.2193418742],"iteration":767,"passed_time":1.337669344,"remaining_time":0.4040876144},
{"learn":[0.2190992545],"iteration":768,"passed_time":1.339449878,"remaining_time":0.4023575056},
{"learn":[0.2188392977],"iteration":769,"passed_time":1.341423746,"remaining_time":0.4006850151},
{"learn":[0.2185607849],"iteration":770,"passed_time":1.343059436,"remaining_time":0.3989112981},
{"learn":[0.2183409666],"iteration":771,"passed_time":1.344849884,"remaining_time":0.3971836446},
{"learn":[0.2180607341],"iteration":772,"passed_time":1.346598839,"remaining_time":0.3954436436},
{"learn":[0.2178315734],"iteration":773,"passed_time":1.348369262,"remaining_time":0.3937098879},
{"learn":[0.2175646099],"iteration":774,"passed_time":1.349965363,"remaining_time":0.3919254279},
{"learn":[0.2173349412],"iteration":775,"passed_time":1.351781381,"remaining_time":0.3902049347},
{"learn":[0.2170852237],"iteration":776,"passed_time":1.35309778,"remaining_time":0.3883408042},
{"learn":[0.2168752743],"iteration":777,"passed_time":1.354828945,"remaining_time":0.3865964342},
{"learn":[0.2165919347],"iteration":778,"passed_time":1.356500196,"remaining_time":0.3848351004},
{"learn":[0.2163612177],"iteration":779,"passed_time":1.358133595,"remaining_time":0.3830633216},
{"learn":[0.2161428184],"iteration":780,"passed_time":1.359932948,"remaining_time":0.3813384324},
{"learn":[0.2159732887],"iteration":781,"passed_time":1.360968693,"remaining_time":0.3794004796},
{"learn":[0.2158448884],"iteration":782,"passed_time":1.361954121,"remaining_time":0.3774508868},
{"learn":[0.2156331389],"iteration":783,"passed_time":1.363657448,"remaining_time":0.3757015418},
{"learn":[0.2153183334],"iteration":784,"passed_time":1.365134444,"remaining_time":0.3738903255},
{"learn":[0.2150519891],"iteration":785,"passed_time":1.366862428,"remaining_time":0.3721482946},
{"learn":[0.2147937582],"iteration":786,"passed_time":1.36848527,"remaining_time":0.3703778431},
{"learn":[0.2147504387],"iteration":787,"passed_time":1.369180384,"remaining_time":0.3683581744},
{"learn":[0.2144877754],"iteration":788,"passed_time":1.370820841,"remaining_time":0.3665946736},
{"learn":[0.2142844294],"iteration":789,"passed_time":1.372478015,"remaining_time":0.3648359281},
{"learn":[0.2140546821],"iteration":790,"passed_time":1.374008009,"remaining_time":0.3630438354},
{"learn":[0.213762141],"iteration":791,"passed_time":1.375518013,"remaining_time":0.3612471549},
{"learn":[0.2134828222],"iteration":792,"passed_time":1.377153518,"remaining_time":0.3594839573},
{"learn":[0.2132388967],"iteration":793,"passed_time":1.378966972,"remaining_time":0.3577672496},
{"learn":[0.2129593807],"iteration":794,"passed_time":1.380654581,"remaining_time":0.356017848},
{"learn":[0.2126980775],"iteration":795,"passed_time":1.382286929,"remaining_time":0.354254439},
{"learn":[0.2124630995],"iteration":796,"passed_time":1.383838818,"remaining_time":0.3524708659},
{"learn":[0.212218248],"iteration":797,"passed_time":1.385614067,"remaining_time":0.3507444129},
{"learn":[0.2120236423],"iteration":798,"passed_time":1.387161411,"remaining_time":0.3489605052},
{"learn":[0.2117744022],"iteration":799,"passed_time":1.38868971,"remaining_time":0.3471724275},
{"learn":[0.2114556893],"iteration":800,"passed_time":1.390498029,"remaining_time":0.3454545665},
{"learn":[0.2111773918],"iteration":801,"passed_time":1.392145715,"remaining_time":0.3436968224},
{"learn":[0.2111431698],"iteration":802,"passed_time":1.392982291,"remaining_time":0.3417403628},
{"learn":[0.2108921806],"iteration":803,"passed_time":1.394586011,"remaining_time":0.3399737041},
{"learn":[0.2106409049],"iteration":804,"passed_time":1.396225926,"remaining_time":0.3382162182},
{"learn":[0.2104046368],"iteration":805,"passed_time":1.397643321,"remaining_time":0.3364054643},
{"learn":[0.210139575],"iteration":806,"passed_time":1.3990969,"remaining_time":0.3346043391},
{"learn":[0.2099405708],"iteration":807,"passed_time":1.400883483,"remaining_time":0.3328832039},
{"learn":[0.2096941629],"iteration":808,"passed_time":1.402562783,"remaining_time":0.331136578},
{"learn":[0.2094315351],"iteration":809,"passed_time":1.404143504,"remaining_time":0.3293669947},
{"learn":[0.2091999717],"iteration":810,"passed_time":1.405853399,"remaining_time":0.3276279808},
{"learn":[0.2089980574],"iteration":811,"passed_time":1.407497266,"remaining_time":0.3258737512},
{"learn":[0.2087503207],"iteration":812,"passed_time":1.409126092,"remaining_time":0.3241163335},
{"learn":[0.2085106111],"iteration":813,"passed_time":1.410699289,"remaining_time":0.3223465205},
{"learn":[0.2082915675],"iteration":814,"passed_time":1.412545566,"remaining_time":0.3206391776},
{"learn":[0.2080851412],"iteration":815,"passed_time":1.414236312,"remaining_time":0.3188964233},
{"learn":[0.207819755],"iteration":816,"passed_time":1.415954175,"remaining_time":0.3171598704},
{"learn":[0.2075847574],"iteration":817,"passed_time":1.417683315,"remaining_time":0.3154258719},
{"learn":[0.2072851752],"iteration":818,"passed_time":1.419290511,"remaining_time":0.313664936},
{"learn":[0.2071356647],"iteration":819,"passed_time":1.420275691,"remaining_time":0.3117678346},
{"learn":[0.2068709578],"iteration":820,"passed_time":1.421998089,"remaining_time":0.310033688},
{"learn":[0.2066530042],"iteration":821,"passed_time":1.423763011,"remaining_time":0.3083087785},
{"learn":[0.2064225824],"iteration":822,"passed_time":1.42538034,"remaining_time":0.3065520293},
{"learn":[0.2061777068],"iteration":823,"passed_time":1.427036002,"remaining_time":0.3048038062},
{"learn":[0.2059249265],"iteration":824,"passed_time":1.428635788,"remaining_time":0.3030439551},
{"learn":[0.2056436699],"iteration":825,"passed_time":1.43029468,"remaining_time":0.3012969422},
{"learn":[0.2053944667],"iteration":826,"passed_time":1.431751072,"remaining_time":0.2995077816},
{"learn":[0.2051864191],"iteration":827,"passed_time":1.433290376,"remaining_time":0.2977366482},
{"learn":[0.2049155517],"iteration":828,"passed_time":1.434939681,"remaining_time":0.295988764},
{"learn":[0.2046477912],"iteration":829,"passed_time":1.436512064,"remaining_time":0.2942253625},
{"learn":[0.2043696897],"iteration":830,"passed_time":1.438095898,"remaining_time":0.2924647493},
{"learn":[0.2041128271],"iteration":831,"passed_time":1.439751315,"remaining_time":0.2907190155},
{"learn":[0.2038896197],"iteration":832,"passed_time":1.441397833,"remaining_time":0.2889717144},
{"learn":[0.2036392436],"iteration":833,"passed_time":1.443045093,"remaining_time":0.2872248028},
{"learn":[0.2034408582],"iteration":834,"passed_time":1.444767963,"remaining_time":0.2854930705},
{"learn":[0.2031920196],"iteration":835,"passed_time":1.446483785,"remaining_time":0.283759977},
{"learn":[0.2029883602],"iteration":836,"passed_time":1.448041681,"remaining_time":0.2819961697},
{"learn":[0.2027503658],"iteration":837,"passed_time":1.449741306,"remaining_time":0.2802602525},
{"learn":[0.2025209227],"iteration":838,"passed_time":1.451287402,"remaining_time":0.2784949604},
{"learn":[0.2023030716],"iteration":839,"passed_time":1.453058438,"remaining_time":0.2767730359},
{"learn":[0.2020468745],"iteration":840,"passed_time":1.454948926,"remaining_time":0.2750735782},
{"learn":[0.2018300258],"iteration":841,"passed_time":1.45673577,"remaining_time":0.2733542181},
{"learn":[0.2015525685],"iteration":842,"passed_time":1.458431537,"remaining_time":0.2716177359},
{"learn":[0.2013747797],"iteration":843,"passed_time":1.459867208,"remaining_time":0.2698332755},
{"learn":[0.2011389656],"iteration":844,"passed_time":1.461284353,"remaining_time":0.2680462422},
{"learn":[0.2009660512],"iteration":845,"passed_time":1.463073132,"remaining_time":0.2663277332},
{"learn":[0.2007693857],"iteration":846,"passed_time":1.46464581,"remaining_time":0.2645700224},
{"learn":[0.2005158905],"iteration":847,"passed_time":1.466112112,"remaining_time":0.2627936805},
{"learn":[0.2002596396],"iteration":848,"passed_time":1.467710565,"remaining_time":0.2610415729},
{"learn":[0.2000849756],"iteration":849,"passed_time":1.469408365,"remaining_time":0.2593073586},
{"learn":[0.1998618428],"iteration":850,"passed_time":1.471054214,"remaining_time":0.2575641339},
{"learn":[0.1996284077],"iteration":851,"passed_time":1.472814725,"remaining_time":0.2558410555},
{"learn":[0.1993597794],"iteration":852,"passed_time":1.474537508,"remaining_time":0.2541113877},
{"learn":[0.1990879966],"iteration":853,"passed_time":1.476273058,"remaining_time":0.2523839185},
{"learn":[0.1988585081],"iteration":854,"passed_time":1.477932742,"remaining_time":0.2506435644},
{"learn":[0.1986222578],"iteration":855,"passed_time":1.47960319,"remaining_time":0.2489052096},
{"learn":[0.1985906242],"iteration":856,"passed_time":1.480259796,"remaining_time":0.2469978423},
{"learn":[0.1983100942],"iteration":857,"passed_time":1.482022084,"remaining_time":0.2452763822},
{"learn":[0.1981008654],"iteration":858,"passed_time":1.483586302,"remaining_time":0.2435223149},
{"learn":[0.1978457481],"iteration":859,"passed_time":1.485285736,"remaining_time":0.2417907012},
{"learn":[0.1976026766],"iteration":860,"passed_time":1.486979074,"remaining_time":0.240058178},
{"learn":[0.197364826],"iteration":861,"passed_time":1.488634895,"remaining_time":0.2383197395},
{"learn":[0.1971527675],"iteration":862,"passed_time":1.490278056,"remaining_time":0.2365794828},
{"learn":[0.1969095876],"iteration":863,"passed_time":1.491855817,"remaining_time":0.2348291563},
{"learn":[0.1967028986],"iteration":864,"passed_time":1.493340994,"remaining_time":0.2330647794},
{"learn":[0.1964497071],"iteration":865,"passed_time":1.495039518,"remaining_time":0.2313340594},
{"learn":[0.1964383537],"iteration":866,"passed_time":1.495679018,"remaining_time":0.2294409566},
{"learn":[0.1962173843],"iteration":867,"passed_time":1.497236465,"remaining_time":0.2276903381},
{"learn":[0.1959608393],"iteration":868,"passed_time":1.49872756,"remaining_time":0.2259301615},
{"learn":[0.195748578],"iteration":869,"passed_time":1.500269848,"remaining_time":0.2241782532},
{"learn":[0.1955453704],"iteration":870,"passed_time":1.502220691,"remaining_time":0.2224873353},
{"learn":[0.1953326389],"iteration":871,"passed_time":1.504829947,"remaining_time":0.2208924693},
{"learn":[0.1951253325],"iteration":872,"passed_time":1.507161593,"remaining_time":0.2192548938},
{"learn":[0.1949131118],"iteration":873,"passed_time":1.508740004,"remaining_time":0.2175071401},
{"learn":[0.1946849259],"iteration":874,"passed_time":1.510728594,"remaining_time":0.2158183706},
{"learn":[0.1944322337],"iteration":875,"passed_time":1.512838148,"remaining_time":0.2141460392},
{"learn":[0.1942409507],"iteration":876,"passed_time":1.514536028,"remaining_time":0.2124149732},
{"learn":[0.1940550858],"iteration":877,"passed_time":1.516434096,"remaining_time":0.2107117993},
{"learn":[0.1938385406],"iteration":878,"passed_time":1.518088628,"remaining_time":0.2089746576},
{"learn":[0.1936238602],"iteration":879,"passed_time":1.519931739,"remaining_time":0.207263419},
{"learn":[0.1934145497],"iteration":880,"passed_time":1.521423918,"remaining_time":0.2055044793},
{"learn":[0.1932297355],"iteration":881,"passed_time":1.52302664,"remaining_time":0.2037609337},
{"learn":[0.1930314502],"iteration":882,"passed_time":1.524563616,"remaining_time":0.2020089955},
{"learn":[0.1927806099],"iteration":883,"passed_time":1.526295772,"remaining_time":0.2002831556},
{"learn":[0.192542572],"iteration":884,"passed_time":1.527930979,"remaining_time":0.1985447035},
{"learn":[0.1922814107],"iteration":885,"passed_time":1.529733073,"remaining_time":0.1968279575},
{"learn":[0.1920370132],"iteration":886,"passed_time":1.531611661,"remaining_time":0.195120764},
{"learn":[0.1918294111],"iteration":887,"passed_time":1.533105513,"remaining_time":0.1933646593},
{"learn":[0.1915699875],"iteration":888,"passed_time":1.535197673,"remaining_time":0.191683849},
{"learn":[0.1913859539],"iteration":889,"passed_time":1.53712939,"remaining_time":0.1899822842},
{"learn":[0.191165523],"iteration":890,"passed_time":1.538738589,"remaining_time":0.1882407477},
{"learn":[0.1909581217],"iteration":891,"passed_time":1.540528824,"remaining_time":0.1865214271},
{"learn":[0.1907300247],"iteration":892,"passed_time":1.542142768,"remaining_time":0.1847808244},
{"learn":[0.1905340351],"iteration":893,"passed_time":1.543770663,"remaining_time":0.1830421591},
{"learn":[0.1903275949],"iteration":894,"passed_time":1.545298072,"remaining_time":0.1812919526},
{"learn":[0.1901469262],"iteration":895,"passed_time":1.547007409,"remaining_time":0.17956336},
{"learn":[0.1899095218],"iteration":896,"passed_time":1.548804686,"remaining_time":0.1778449082},
{"learn":[0.1896646999],"iteration":897,"passed_time":1.550223439,"remaining_time":0.176083286},
{"learn":[0.189474396],"iteration":898,"passed_time":1.551856124,"remaining_time":0.1743464611},
{"learn":[0.1892871421],"iteration":899,"passed_time":1.55347394,"remaining_time":0.1726082156},
{"learn":[0.1890790133],"iteration":900,"passed_time":1.555032164,"remaining_time":0.1708636895},
{"learn":[0.1890013108],"iteration":901,"passed_time":1.555818018,"remaining_time":0.1690356605},
{"learn":[0.1887676508],"iteration":902,"passed_time":1.557577826,"remaining_time":0.1673145616},
{"learn":[0.188537043],"iteration":903,"passed_time":1.559551042,"remaining_time":0.1656160399},
{"learn":[0.1882989453],"iteration":904,"passed_time":1.561104536,"remaining_time":0.1638728518},
{"learn":[0.1882588337],"iteration":905,"passed_time":1.56182926,"remaining_time":0.1620440954},
{"learn":[0.1880594851],"iteration":906,"passed_time":1.563508826,"remaining_time":0.160315679},
{"learn":[0.1878310072],"iteration":907,"passed_time":1.565543003,"remaining_time":0.1586232999},
{"learn":[0.1876297975],"iteration":908,"passed_time":1.567519555,"remaining_time":0.1569243999},
{"learn":[0.1874239004],"iteration":909,"passed_time":1.569414049,"remaining_time":0.1552167741},
{"learn":[0.1871999674],"iteration":910,"passed_time":1.571409493,"remaining_time":0.1535186003},
{"learn":[0.1871172017],"iteration":911,"passed_time":1.572721756,"remaining_time":0.1517538537},
{"learn":[0.1869337129],"iteration":912,"passed_time":1.574445328,"remaining_time":0.150029292},
{"learn":[0.186706227],"iteration":913,"passed_time":1.57625598,"remaining_time":0.1483129259},
{"learn":[0.1864967935],"iteration":914,"passed_time":1.578043885,"remaining_time":0.1465942407},
{"learn":[0.1862737852],"iteration":915,"passed_time":1.579699406,"remaining_time":0.1448632643},
{"learn":[0.1860691474],"iteration":916,"passed_time":1.581312241,"remaining_time":0.1431285889},
{"learn":[0.1858615685],"iteration":917,"passed_time":1.582831123,"remaining_time":0.1413857866},
{"learn":[0.1856261967],"iteration":918,"passed_time":1.584440412,"remaining_time":0.13965144},
{"learn":[0.185390337],"iteration":919,"passed_time":1.586152635,"remaining_time":0.1379263161},
{"learn":[0.1851896511],"iteration":920,"passed_time":1.587952097,"remaining_time":0.1362087032},
{"learn":[0.1849533709],"iteration":921,"passed_time":1.58950108,"remaining_time":0.1344697226},
{"learn":[0.1847562049],"iteration":922,"passed_time":1.591207899,"remaining_time":0.1327443209},
{"learn":[0.1845506396],"iteration":923,"passed_time":1.592741069,"remaining_time":0.1310046766},
{"learn":[0.1843338128],"iteration":924,"passed_time":1.594545418,"remaining_time":0.1292874663},
{"learn":[0.1841251883],"iteration":925,"passed_time":1.59613382,"remaining_time":0.1275528107},
{"learn":[0.1838886904],"iteration":926,"passed_time":1.597706175,"remaining_time":0.1258172069},
{"learn":[0.1836723101],"iteration":927,"passed_time":1.599558136,"remaining_time":0.1241036485},
{"learn":[0.1834925955],"iteration":928,"passed_time":1.601261676,"remaining_time":0.1223784488},
{"learn":[0.1832512941],"iteration":929,"passed_time":1.602935405,"remaining_time":0.120651052},
{"learn":[0.1830581659],"iteration":930,"passed_time":1.604625599,"remaining_time":0.1189249907},
{"learn":[0.1830450469],"iteration":931,"passed_time":1.605277487,"remaining_time":0.1171232502},
{"learn":[0.1827926411],"iteration":932,"passed_time":1.60701891,"remaining_time":0.1154022154},
{"learn":[0.1825927277],"iteration":933,"passed_time":1.608724687,"remaining_time":0.1136786181},
{"learn":[0.1824175128],"iteration":934,"passed_time":1.610344306,"remaining_time":0.1119490694},
{"learn":[0.1822155087],"iteration":935,"passed_time":1.612172877,"remaining_time":0.1102340428},
{"learn":[0.1819937191],"iteration":936,"passed_time":1.61403147,"remaining_time":0.1085207926},
{"learn":[0.1819183053],"iteration":937,"passed_time":1.61489996,"remaining_time":0.1067417884},
{"learn":[0.1816888686],"iteration":938,"passed_time":1.616143812,"remaining_time":0.1049891081},
{"learn":[0.1814640503],"iteration":939,"passed_time":1.617781003,"remaining_time":0.1032626172},
{"learn":[0.18124205],"iteration":940,"passed_time":1.619374074,"remaining_time":0.1015335498},
{"learn":[0.1810308422],"iteration":941,"passed_time":1.620875354,"remaining_time":0.09979911944},
{"learn":[0.1808047497],"iteration":942,"passed_time":1.622381544,"remaining_time":0.09806548039},
{"learn":[0.1806597467],"iteration":943,"passed_time":1.623916286,"remaining_time":0.09633401694},
{"learn":[0.1804982167],"iteration":944,"passed_time":1.625674766,"remaining_time":0.09461599166},
{"learn":[0.180309398],"iteration":945,"passed_time":1.627398732,"remaining_time":0.09289591072},
{"learn":[0.1801259037],"iteration":946,"passed_time":1.62901126,"remaining_time":0.09116958479},
{"learn":[0.1799179873],"iteration":947,"passed_time":1.630198578,"remaining_time":0.08942017516},
{"learn":[0.1797124199],"iteration":948,"passed_time":1.631900208,"remaining_time":0.08769958969},
{"learn":[0.1795084662],"iteration":949,"passed_time":1.633529639,"remaining_time":0.08597524416},
{"learn":[0.1793220785],"iteration":950,"passed_time":1.634924354,"remaining_time":0.08423900456},
{"learn":[0.1791250968],"iteration":951,"passed_time":1.636818274,"remaining_time":0.08252865247},
{"learn":[0.1789451575],"iteration":952,"passed_time":1.63851245,"remaining_time":0.08080806418},
{"learn":[0.1787531708],"iteration":953,"passed_time":1.640167523,"remaining_time":0.07908564576},
{"learn":[0.1785582363],"iteration":954,"passed_time":1.641743173,"remaining_time":0.07735962594},
{"learn":[0.1783822018],"iteration":955,"passed_time":1.643329857,"remaining_time":0.07563442855},
{"learn":[0.1782036658],"iteration":956,"passed_time":1.645068738,"remaining_time":0.07391635918},
{"learn":[0.1780333991],"iteration":957,"passed_time":1.646762512,"remaining_time":0.0721962688},
{"learn":[0.1778823],"iteration":958,"passed_time":1.648375741,"remaining_time":0.07047278976},
{"learn":[0.1776673902],"iteration":959,"passed_time":1.65020181,"remaining_time":0.06875840875},
{"learn":[0.1774814113],"iteration":960,"passed_time":1.651716551,"remaining_time":0.06703116075},
{"learn":[0.1772961783],"iteration":961,"passed_time":1.653245647,"remaining_time":0.0653049216},
{"learn":[0.1771164151],"iteration":962,"passed_time":1.655065096,"remaining_time":0.06359024773},
{"learn":[0.1769258425],"iteration":963,"passed_time":1.656641899,"remaining_time":0.06186629497},
{"learn":[0.1767607757],"iteration":964,"passed_time":1.658295231,"remaining_time":0.06014542289},
{"learn":[0.176533669],"iteration":965,"passed_time":1.660057505,"remaining_time":0.058428525},
{"learn":[0.1763612673],"iteration":966,"passed_time":1.661592932,"remaining_time":0.05670379189},
{"learn":[0.1761629128],"iteration":967,"passed_time":1.663211692,"remaining_time":0.05498220468},
{"learn":[0.175946816],"iteration":968,"passed_time":1.664770451,"remaining_time":0.05325891021},
{"learn":[0.1757730634],"iteration":969,"passed_time":1.666450089,"remaining_time":0.05153969347},
{"learn":[0.1757547378],"iteration":970,"passed_time":1.667049746,
{"learn":[0.1734963851],"itera,
{"learn":[0.175595476],"iteration":971,"passed_time":1.668476973,,
{"learn":[0.1733441077],"iter,
{"learn":[0.1753736612],"iteration":972,"passed_time":1.670092739,,
{"learn":[0.1731421327],"iter,
{"learn":[0.1751994956],"iteration":973,"passed_time":1.671777599,,
{"learn":[0.1729796681],"iter,
{"learn":[0.1750091595],"iteration":974,"passed_time":1.67346674,",
{"learn":[0.1727709182],"ite,
{"learn":[0.1748215962],"iteration":975,"passed_time":1.674943158,",
{"learn":[0.1725709306],"ite,
{"learn":[0.1746681931],"iteration":976,"passed_time":1.676546588,",
{"learn":[0.1723725734],"ite,
{"learn":[0.174506135],"iteration":977,"passed_time":1.678112448,"r,
{"learn":[0.1721945965],"it,
{"learn":[0.1744162461],"iteration":978,"passed_time":1.6790901,"rem,
{"learn":[0.1720145907],",
{"learn":[0.1742192196],"iteration":979,"passed_time":1.680687731,"rem,
{"learn":[0.1718487085],",
{"learn":[0.1740115822],"iteration":980,"passed_time":1.682397223,"rem,
{"learn":[0.1716726662],",
{"learn":[0.1738792942],"iteration":981,"passed_time":1.684126956,"rem,
{"learn":[0.1714686768],,
{"learn":[0.1736989998],"iteration":982,"passed_time":1.685643814,"rema,
{"learn":[0.1713050804],,
{"learn":[0.1735647578],"iteration":983,"passed_time":1.68727798,"remai,
{"learn":[0.1710894917],
{"learn":[0.1733956774],"iteration":984,"passed_time":1.688895202,"remai,
{"learn":[0.1708981805],
{"learn":[0.1732200032],"iteration":985,"passed_time":1.690695764,"remai,
{"learn":[0.1706948016,
{"learn":[0.1730406464],"iteration":986,"passed_time":1.692277356,"remain,
{"learn":[0.1704733406,
{"learn":[0.1728488954],"iteration":987,"passed_time":1.693995918,"remain,
{"learn":[0.170279503,
{"learn":[0.1726624182],"iteration":988,"passed_time":1.695639903,"remaini,
{"learn":[0.170093960,
{"learn":[0.1724517583],"iteration":989,"passed_time":1.697253425,"remaini,
{"learn":[0.169927916,
{"learn":[0.1722680006],"iteration":990,"passed_time":1.698898064,"remaini,
{"learn":[0.169733090,
{"learn":[0.172106635],"iteration":991,"passed_time":1.700334581,"remainin,
{"learn":[0.16958615,
{"learn":[0.171879018],"iteration":992,"passed_time":1.702068829,"remainin,
{"learn":[0.1694204,
{"learn":[0.1717404998],"iteration":993,"passed_time":1.703675233,"remaining,
{"learn":[0.1692556,
{"learn":[0.1715326521],"iteration":994,"passed_time":1.705607733,"remaining_,
{"learn":[0.1690645,
{"learn":[0.1715066668],"iteration":995,"passed_time":1.706332958,"remaining_,
{"learn":[0.1688959,
{"learn":[0.1713497587],"iteration":996,"passed_time":1.708074439,"remaining,
{"learn":[0.16866450,
{"learn":[0.1711377333],"iteration":997,"passed_time":1.709883123,"remaining,
{"learn":[0.16848429,
{"learn":[0.1709745172],"iteration":998,"passed_time":1.711530432,"remainin,
{"learn":[0.168288655,
{"learn":[0.1708074596],"iteration":999,"passed_time":1.71311756,"remaining_time":0}
]}